Workbook
Name HOMOL: '[1]TABLA DE NOMBRES'!#REF!
Name HOMOL: '[1]TABLA DE NOMBRES'!#REF!
Name HOMOL: '[1]TABLA DE NOMBRES'!#REF!
Name _Toc26271466: Equipos!$G$35

Sheet Hoja de CIERRE
B1: HOJA DE CIERRE PROPUESTA
I3: IMA Servicios Industriales Argentina S.A.
B5: NOMBRE PROPUESTA: | I5: [NOMBRE DE LA PROPUESTA]
B7: NOMBRE CLIENTE: | I7: [CLIENTE] | AA7: FECHA: | AD7: 46199
B9: REFERENCIA CLIENTE: | I9: [Nº LICITACIÓN / PROCESO] | AA9: C.I.
B11: SOLICITADO POR: | U11: CARGO:
B13: COTIZADO POR: | I13: IMA | U13: Vendedor: | X13: IMA
B14: REVISADO POR: | I14: IMA
B16: OFERTA Nº: | I16: [OFERTA Nº]
B18: OBJETIVO Y ALCANCE:
B20: [OBJETIVO Y ALCANCE DEL SERVICIO]
B25: GARANTIAS:
J26: SI | L26: NO | N26: DESCRIPCION
B27: SERIEDAD DE LA OFERTA
B28: FIEL CUMPLIMIENTO
B29: RETENCIONES | J29: X | N29: RETENCIÓN DE IVA, IIGG E IIBB
B31: MULTAS:
J32: SI | L32: NO | N32: DESCRIPCION
B33: POR PLAZO DE HITOS | J33: X
B34: PERSONAL | J34: X
B35: EQUIPOS | J35: X
B36: MEDIO AMBIENTE | J36: X
B38: SEGUROS:
J39: SI | L39: NO | N39: DESCRIPCION
B40: ACCIDENTES TRABAJO Y EP | J40: X | N40: ART
B41: VEHICULOS | J41: X | N41: SEGURO
B42: RESPONSABILIDAD CIVIL | J42: X | N42: SEGURO
B43: ACCIDENTES PERSONALES
AD44: AÑOS
B45: DURACION DEL CONTRATO: | N45: 2 AÑOS | AD45: 1
B47: COMPETENCIA:
B54: TIPO DE CONTRATO: | N54: VALOR POR HH
B56: MONEDA Y REAJUSTABILIDAD: | N56: PESOS ARGENTINOS
B58: FORMA DE PAGO: | N58: 30 DIAS FECHA FACTURA
B60: PROGRAMA DE CONTROL DE RIESGOS:
B62: PLAN DE ASEGURAMIENTO DE CALIDAD:
B65: TOTAL COSTO DIRECTOS DE EXPLOTACIÓN + IMP. DIRECTOS | X65: =+'Sintesis Economica'!G18+'Sintesis Economica'!G20 | AF65: MES
B66: MARGEN BRUTO (RESULTADO OPERACIONAL) | U66: =+X66/X67 | X66: =+X67-X65 | AF66: MES | AH66: =+X66/X65 | AI66: MARGEN IMA
B67: PRECIO DE VENTA (sin IVA) | X67: =+'Sintesis Economica'!G24 | AF67: MES
B69: FIRMAS COMITE DE CIERRE:

Sheet Sintesis Economica
B1: SINTESIS DE PRESUPUESTO DE VENTA
B2: CLIENTE: | C2: =+'Hoja de CIERRE'!I7 | I2: Cotizó: | J2: =+'Hoja de CIERRE'!I13
B3: SERVICIO PROYECTO : | C3: =+'Hoja de CIERRE'!I5 | I3: Vendió: | J3: =+'Hoja de CIERRE'!X13
I4: Revisó: | J4: =+'Hoja de CIERRE'!I14
B5: PLIEGO / E.T.P.: | C5: =+'Hoja de CIERRE'!I9 | I5: Fecha: | J5: =+'Hoja de CIERRE'!AD7
B6: OFERTA N°: | C6: =+'Hoja de CIERRE'!I16 | I6: Revisión | J6: 0
C10: COSTOS | E10: TOTAL HH | F10: TOTAL Ho | G10: VALOR MES | H10: VALOR AÑO | I10: VALOR CONTRATO | N10: CONCEPTOS | O10: PONDERACION PORCENTUAL | P10: INDICES DE ACTULIZACION
C11: 1 | D11: MANO DE OBRA | E11: ='1 MANO DE OBRA'!L44 | F11: =+E11/191 | G11: ='Presupuesto Interno'!E11 | H11: =+G11*12 | I11: =+H11*'Hoja de CIERRE'!$AD$45 | N11: MANO DE OBRA | O11: ='Presupuesto de VENTA'!J13 | P11: Escala Salarial U.O.M. Oct-09 | R11: =+'Hoja de CIERRE'!U66*50% | S11: MARGEN A MANO DE OBRA
C12: 2 | D12: SUMINISTRO DE MATERIALES | G12: ='Presupuesto Interno'!E19 | H12: =+G12*12 | I12: =+H12*'Hoja de CIERRE'!$AD$45 | N12: MATERIALES | O12: 0 | P12: -------
C13: 3 | D13: SUMINISTRO DE INSUMOS | G13: ='Presupuesto Interno'!E25 | H13: =+G13*12 | I13: =+H13*'Hoja de CIERRE'!$AD$45 | N13: INSUMOS CONSUMIBLES + EPP | O13: ='Presupuesto de VENTA'!J25 | P13: IPIM - NG Oct-09
C14: 4 | D14: SUBCONTRATACIONES | G14: ='Presupuesto Interno'!E33 | H14: =+G14*12 | I14: =+H14*'Hoja de CIERRE'!$AD$45 | N14: COMBUSTIBLES | O14: ='Presupuesto de VENTA'!J33 | P14: Precio Gas-Oil Oct-09
C15: 5 | D15: AMORTIZACIONES | G15: ='Presupuesto Interno'!E40 | H15: =+G15*12 | I15: =+H15*'Hoja de CIERRE'!$AD$45 | N15: AMORTIZACIONES | O15: ='Presupuesto de VENTA'!J40 | P15: Dólar Estadounidense 3,80 $/u$s
C16: 6 | D16: GASTOS GENERALES DE OPERACIÓN (DIRECTOS) | G16: ='Presupuesto Interno'!E48 | H16: =+G16*12 | I16: =+H16*'Hoja de CIERRE'!$AD$45 | N16: SUBCONTRATACIONES + GTOS GRALES | O16: =1-SUM(O11:O15) | P16: IPIM - NG Oct-09
D18: TOTAL COSTOS DIRECTOS DE EXPLOTACIÓN | G18: =SUM(G11:G16) | H18: =SUM(H11:H16) | I18: =SUM(I11:I16) | O18: =+SUM(O11:O16)
D20: IMPUESTOS DIRECTOS DE FACTURACIÓN ====>>> | G20: ='Presupuesto de VENTA'!G7 | H20: =+G20*12 | I20: =+H20*'Hoja de CIERRE'!$AD$45
D22: MARGEN BRUTO / UTILIDAD BRUTA | E22: =+G22/G24 | G22: =+G24-G18-G20 | H22: =+G22*12 | I22: =+H22*'Hoja de CIERRE'!$AD$45
C24: PRECIO DE VENTA TOTAL SIN IVA | E24: (Costo + Impuestos + Utilidad) | G24: ='Presupuesto de VENTA'!H7 | H24: =+G24*12 | I24: =+H24*'Hoja de CIERRE'!$AD$45
C26: I.V.A. | E26: 0.21 | G26: =G24*E26 | H26: =+G26*12 | I26: =+H26*'Hoja de CIERRE'!$AD$45
C28: PRECIO DE VENTA TOTAL CON I.V.A. | G28: =+G24+G26 | H28: =+H24+H26 | I28: =+I24+I26
C31: VENTA NETA ( Despues de IVA e Impuestos Directos de Facturación) | G31: =+G28-G26-G20 | H31: =+H28-H26-H20 | I31: =+I28-I26-I20
C33: GASTOS GENERALES DE ESTRUCTURA | E33: 0 | G33: =+G31*$E$33 | H33: =+H31*$E$33 | I33: =+I31*$E$33
C35: UTILIDAD NETA OPERATIVA MENSUAL | F35: =+G35/G31 | G35: =+G31-G18-G33 | H35: =+H31-H18-H33 | I35: =+I31-I18-I33
C36: UTILIDAD NETA OPERATIVA TOTAL (Acumulada) - Estimación | G36: =+I35
C38: (INVERSIÓN / FACTURACIÓN) ---- INVERSIÓN | F38: =+G38/$G$24 | G38: =+'5 AMORTIZACIÓN'!F89
C39: R.O.I. (RENTABILIDAD SOBRE LA INVERSIÓN) | G39: =((G36/G38)/('Hoja de CIERRE'!$AD$45))
B42: ANALISIS COMPARATIVO DE ITMS UNITARIOS
E44: COSTO MO | F44: PRECIO VENTA | G44: UTILIDAD NETA OPERATIVA | J44: MAKE-UP
B46: POR HOMBRE (Ho) | E46: =+G11/F11 | F46: =+G24/F11 | G46: =+G35/F11 | J46: =+F46/E46
B48: POR HORA HOMRE (HH) | E48: =+G11/E11 | F48: =+G24/E11 | G48: =+G35/E11 | J48: =+F48/E48
B52: AUTORIZADO POR:
B54: FUNCIÓN/CARGO: | F54: FIRMA:
B57: COMENTARIOS:

Sheet Presupuesto de VENTA
B1: PRESUPUESTO INTERNO DE VENTA
C2: CLIENTE: | D2: =+'Sintesis Economica'!C2 | I2: J. de PROYECTO: | J2: =+'Sintesis Economica'!J2
C3: OBRA : | D3: =+'Sintesis Economica'!C3 | I3: Elaboró: | J3: =+'Sintesis Economica'!J3
C4: PLIEGO / E.T.P.: | D4: =+'Sintesis Economica'!C5 | I4: Revisó: | J4: =+'Sintesis Economica'!J4
C5: OFERTA N°: | D5: =+'Sintesis Economica'!C6 | I5: Fecha: | J5: =+'Sintesis Economica'!J5
H6: =6*H7
B7: MARGEN BRUTO FINAL | D7: PRECIO DE VENTA CON IMPUESTOS | F7: =+(5+1.2+0.5)% | G7: =-H11+H11/(1-F7) | H7: =+H11+G7 | I7: =+H7/$E$9 | J7: =H7*12 | K7: =I7/28000
H8: =H7-H41-H74 | I8: =H8/E9
B9: =+(H7-F11-G7)/H7 | D9: DOTACIÓN | E9: ='Presupuesto Interno'!D7 | F9: COSTOS | G9: MARGEN BRUTO (sin impuestos) | H9: PRECIO VENTA (sin impuestos) | I9: PRECIO VENTA POR H-H | J9: % DE DISTRIBUCIÓN | L9: =(H7-G7)/F11-1 | N9: MARGEN BRUTO TRADICIONAL | O9: factor he | Q9: 2 OP
O10: Bruto | P10: General | Q10: Total
B11: ITEMS | F11: =F13+F19+F25+F33+F40+F48 | G11: =+(H11-F11)/H11 | H11: =+H13+H19+H25+H33+H40+H48 | I11: =H11/$E$9 | J11: =+SUM(J13:J48) | N11: ='1 MANO DE OBRA'!B17 | O11: ='1 MANO DE OBRA'!F17 | P11: =$L$4 | Q11: =O11+P11 | R11: =AVERAGE(Q11:Q12)
N12: ='1 MANO DE OBRA'!B18 | O12: ='1 MANO DE OBRA'!F18 | P12: =$L$4 | Q12: =O12+P12
B13: 1- MANO DE OBRA | F13: =SUM(F14:F17) | G13: =+(H13-F13)/H13 | H13: =SUM(H14:H17) | I13: =H13/$E$9 | J13: =+H13/$H$7 | K13: 0.76586865 | N13: ='1 MANO DE OBRA'!B19 | O13: ='1 MANO DE OBRA'!F19 | P13: =$L$4 | Q13: =(O13+P13)*1.1 | R13: =Q13 | S13: =R13/R11
D14: =+'Presupuesto Interno'!C12 | F14: =+'Presupuesto Interno'!E12 | G14: 0.18 | H14: =+F14/(1-G14)
D15: =+'Presupuesto Interno'!C13 | F15: =+'Presupuesto Interno'!E13 | G15: 0.15 | H15: =+F15/(1-G15) | J15: =F15/$E$9
D16: =+'Presupuesto Interno'!C14 | F16: =+'Presupuesto Interno'!E14 | G16: 0.04 | H16: =+F16/(1-G16)
D17: =+'Presupuesto Interno'!C15 | F17: =+'Presupuesto Interno'!E15 | G17: 0.04 | H17: =+F17/(1-G17)
B19: 2- SUMINISTRO DE MATERIALES | F19: =SUM(F20:F23) | G19: =+(H19-F19)/H19 | H19: =SUM(H20:H23) | I19: =H19/$E$9 | J19: =+H19/$H$7 | K19: 0
D20: =+'Presupuesto Interno'!C20 | F20: =+'Presupuesto Interno'!E20 | G20: 0 | H20: =+F20/(1-G20)
D21: =+'Presupuesto Interno'!C21 | F21: =+'Presupuesto Interno'!E21 | G21: 0 | H21: =+F21/(1-G21)
D22: =+'Presupuesto Interno'!C22 | F22: =+'Presupuesto Interno'!E22 | G22: 0 | H22: =+F22/(1-G22)
D23: =+'Presupuesto Interno'!C23 | F23: =+'Presupuesto Interno'!E23 | G23: 0 | H23: =+F23/(1-G23)
B25: 3- SUMINISTRO DE INSUMOS | F25: =SUM(F26:F31) | G25: =(H25-F25)/H25 | H25: =SUM(H26:H31) | I25: =H25/$E$9 | J25: =+H25/$H$7 | K25: 0.033793843
D26: =+'Presupuesto Interno'!C26 | F26: =+'Presupuesto Interno'!E26 | G26: 0.05 | H26: =+F26/(1-G26) | J26: =F26/$E$9
D27: =+'Presupuesto Interno'!C27 | F27: =+'Presupuesto Interno'!E27 | G27: 0.05 | H27: =+F27/(1-G27) | J27: =F27/$E$9
D28: =+'Presupuesto Interno'!C28 | F28: =+'Presupuesto Interno'!E28 | G28: 0.05 | H28: =+F28/(1-G28) | J28: =F28/$E$9
D29: =+'Presupuesto Interno'!C29 | F29: =+'Presupuesto Interno'!E29 | G29: 0.05 | H29: =+F29/(1-G29) | J29: =F29/$E$9
D30: =+'Presupuesto Interno'!C30 | F30: =+'Presupuesto Interno'!E30 | G30: 0.05 | H30: =+F30/(1-G30) | J30: =F30/$E$9
D31: =+'Presupuesto Interno'!C31 | F31: =+'Presupuesto Interno'!E31 | G31: 0.05 | H31: =+F31/(1-G31)
B33: 4- SUBCONTRATACIONES | F33: =SUM(F34:F38) | G33: =+(H33-F33)/H33 | H33: =SUM(H34:H38) | I33: =H33/$E$9 | J33: =+H33/$H$7 | K33: 0.0093456854
D34: =+'Presupuesto Interno'!C34 | F34: =+'Presupuesto Interno'!E34 | G34: 0.05 | H34: =+F34/(1-G34) | J34: =F34/$E$9
D35: =+'Presupuesto Interno'!C35 | F35: =+'Presupuesto Interno'!E35 | G35: 0.05 | H35: =+F35/(1-G35) | J35: =F35/$E$9
D36: =+'Presupuesto Interno'!C36 | F36: =+'Presupuesto Interno'!E36 | G36: 0.05 | H36: =+F36/(1-G36) | J36: =F36/$E$9
D37: =+'Presupuesto Interno'!C37 | F37: =+'Presupuesto Interno'!E37 | G37: 0.05 | H37: =+F37/(1-G37) | J37: =F37/$E$9
D38: =+'Presupuesto Interno'!C38 | F38: =+'Presupuesto Interno'!E38 | G38: 0.05 | H38: =+F38/(1-G38) | J38: =F38/$E$9
B40: 5- AMORTIZACIONES | F40: =SUM(F41:F46) | G40: =+(H40-F40)/H40 | H40: =SUM(H41:H46) | I40: =H40/$E$9 | J40: =+H40/$H$7 | K40: 0.065203183
D41: =+'Presupuesto Interno'!C41 | F41: =+'Presupuesto Interno'!E41 | G41: 0.05 | H41: =+F41/(1-G41) | J41: =F41/$E$9
D42: =+'Presupuesto Interno'!C42 | F42: =+'Presupuesto Interno'!E42 | G42: 0.05 | H42: =+F42/(1-G42) | J42: =F42/$E$9 | K42: =F42/H7
D43: =+'Presupuesto Interno'!C43 | F43: =+'Presupuesto Interno'!E43 | G43: 0.05 | H43: =+F43/(1-G43) | J43: =F43/$E$9
D44: =+'Presupuesto Interno'!C44 | F44: =+'Presupuesto Interno'!E44 | G44: 0.05 | H44: =+F44/(1-G44) | J44: =F44/$E$9
D45: =+'Presupuesto Interno'!C45 | F45: =+'Presupuesto Interno'!E45 | G45: 0.05 | H45: =+F45/(1-G45) | J45: =F45/$E$9
D46: =+'Presupuesto Interno'!C46 | F46: =+'Presupuesto Interno'!E46 | G46: 0.05 | H46: =+F46/(1-G46) | J46: =F46/$E$9
B48: 6- GASTOS GENERALES | F48: =F50+F55+F61+F67+F73+F80+F88 | G48: =+(H48-F48)/H48 | H48: =+H50+H55+H61+H67+H73+H80+H88 | I48: =H48/$E$9 | J48: =+H48/$H$7 | K48: 0.068788641
C50: 6.1 Servicios | F50: =SUM(F51:F53) | G50: =+(H50-F50)/H50 | H50: =SUM(H51:H53) | K50: 1.0604143
D51: =+'Presupuesto Interno'!C51 | F51: =+'Presupuesto Interno'!E51 | G51: 0.05 | H51: =+F51/(1-G51) | J51: =F51/$E$9
D52: =+'Presupuesto Interno'!C52 | F52: =+'Presupuesto Interno'!E52 | G52: 0.05 | H52: =+F52/(1-G52) | J52: =F52/$E$9
D53: =+'Presupuesto Interno'!C53 | F53: =+'Presupuesto Interno'!E53 | G53: 0.05 | H53: =+F53/(1-G53) | J53: =F53/$E$9
C55: 6.2 Alquileres y Leassing | F55: =SUM(F56:F59) | G55: =+(H55-F55)/H55 | H55: =SUM(H56:H59)
D56: =+'Presupuesto Interno'!C56 | F56: =+'Presupuesto Interno'!E56 | G56: 0.05 | H56: =+F56/(1-G56)
D57: =+'Presupuesto Interno'!C57 | F57: =+'Presupuesto Interno'!E57 | G57: 0.05 | H57: =+F57/(1-G57)
D58: =+'Presupuesto Interno'!C58 | F58: =+'Presupuesto Interno'!E58 | G58: 0.05 | H58: =+F58/(1-G58)
D59: =+'Presupuesto Interno'!C59 | F59: =+'Presupuesto Interno'!E59 | G59: 0.05 | H59: =+F59/(1-G59)
C61: 6.3 Mantenimiento | F61: =SUM(F62:F65) | G61: =+(H61-F61)/H61 | H61: =SUM(H62:H65)
D62: =+'Presupuesto Interno'!C62 | F62: =+'Presupuesto Interno'!E62 | G62: 0.05 | H62: =+F62/(1-G62) | J62: =F62/$E$9
D63: =+'Presupuesto Interno'!C63 | F63: =+'Presupuesto Interno'!E63 | G63: 0.05 | H63: =+F63/(1-G63) | J63: =F63/$E$9
D64: =+'Presupuesto Interno'!C64 | F64: =+'Presupuesto Interno'!E64 | G64: 0.05 | H64: =+F64/(1-G64) | J64: =F64/$E$9
D65: =+'Presupuesto Interno'!C65 | F65: =+'Presupuesto Interno'!E65 | G65: 0.05 | H65: =+F65/(1-G65) | J65: =F65/$E$9
C67: 6.4 Previsiones Operativas | F67: =SUM(F68:F71) | G67: =+(H67-F67)/H67 | H67: =SUM(H68:H71)
D68: =+'Presupuesto Interno'!C68 | F68: =+'Presupuesto Interno'!E68 | G68: 0.05 | H68: =+F68/(1-G68) | J68: =F68/$E$9
D69: =+'Presupuesto Interno'!C69 | F69: =+'Presupuesto Interno'!E69 | G69: 0.05 | H69: =+F69/(1-G69) | J69: =F69/$E$9
D70: =+'Presupuesto Interno'!C70 | F70: =+'Presupuesto Interno'!E70 | G70: 0.05 | H70: =+F70/(1-G70) | J70: =F70/$E$9
D71: =+'Presupuesto Interno'!C71 | F71: =+'Presupuesto Interno'!E71 | G71: 0.05 | H71: =+F71/(1-G71) | J71: =F71/$E$9
C73: 6.5 Seguros | F73: =SUM(F74:F78) | G73: =+(H73-F73)/H73 | H73: =SUM(H74:H78)
D74: =+'Presupuesto Interno'!C74 | F74: =+'Presupuesto Interno'!E74 | G74: 0.05 | H74: =+F74/(1-G74) | J74: =F74/$E$9
D75: =+'Presupuesto Interno'!C75 | F75: =+'Presupuesto Interno'!E75 | G75: 0.05 | H75: =+F75/(1-G75) | J75: =F75/$E$9
D76: =+'Presupuesto Interno'!C76 | F76: =+'Presupuesto Interno'!E76 | G76: 0.05 | H76: =+F76/(1-G76) | J76: =F76/$E$9
D77: =+'Presupuesto Interno'!C77 | F77: =+'Presupuesto Interno'!E77 | G77: 0.05 | H77: =+F77/(1-G77) | J77: =F77/$E$9
D78: =+'Presupuesto Interno'!C78 | F78: =+'Presupuesto Interno'!E78 | G78: 0.05 | H78: =+F78/(1-G78) | J78: =F78/$E$9
C80: 6.6 Otros Gastos Generales | F80: =SUM(F81:F86) | G80: =+(H80-F80)/H80 | H80: =SUM(H81:H86)
D81: =+'Presupuesto Interno'!C81 | F81: =+'Presupuesto Interno'!E81 | G81: 0.05 | H81: =+F81/(1-G81)
D82: =+'Presupuesto Interno'!C82 | F82: =+'Presupuesto Interno'!E82 | G82: 0.05 | H82: =+F82/(1-G82)
D83: =+'Presupuesto Interno'!C83 | F83: =+'Presupuesto Interno'!E83 | G83: 0.05 | H83: =+F83/(1-G83)
D84: =+'Presupuesto Interno'!C84 | F84: =+'Presupuesto Interno'!E84 | G84: 0.05 | H84: =+F84/(1-G84)
D85: =+'Presupuesto Interno'!C85 | F85: =+'Presupuesto Interno'!E85 | G85: 0.05 | H85: =+F85/(1-G85)
D86: =+'Presupuesto Interno'!C86 | F86: =+'Presupuesto Interno'!E86 | G86: 0.05 | H86: =+F86/(1-G86)
C88: 6.7 Viaticos | F88: =SUM(F89:F92) | G88: =+(H88-F88)/H88 | H88: =SUM(H89:H92) | I88: =H88/E9
D89: 6.7.1 Comidas | F89: =+'Presupuesto Interno'!E89 | G89: 0.05 | H89: =+F89/(1-G89) | J89: =F89/$E$9
D90: 6.7.2 Alojamiento | F90: =+'Presupuesto Interno'!E90 | G90: 0.05 | H90: =+F90/(1-G90)
D91: 6.7.3 Traslados | F91: =+'Presupuesto Interno'!E91 | G91: 0.05 | H91: =+F91/(1-G91) | J91: =F91/$E$9
D92: 6.7.4 Vehiculos | F92: =+'Presupuesto Interno'!E92 | G92: 0.05 | H92: =+F92/(1-G92) | J92: =F92/$E$9
E94: Firma Jefe de Proyecto
D105: Indumentaria | E105: =J30*80% | F105: =10000/12/187
D106: Servicio Médico | E106: 1 | F106: 1.9
D107: Transporte | E107: =J91 | F107: =5000/187
D108: Refrigerio | E108: =J89 | F108: =180/8
D109: Otros (EPP) | E109: =20%*E105 | F109: =8.04
D110: Consumibles y herramientas | E110: =J42+J44+J45+J26+J28+J29 | F110: 12.67
D111: Vehiculos y obradores | E111: =J41+J42+J27+J92+J62+J64+J65+J69+J74+J75 | F111: 49.39
D112: Costos Estructura No Operativa | E112: =J15+J35+J51+J52 | F112: 39.9
E113: =SUM(E105:E112) | F113: =SUM(F105:F112)

Sheet Presupuesto Interno
A1: PRESUPUESTO INTERNO DE COSTOS Y GASTOS
B2: CLIENTE: | C2: =+'Sintesis Economica'!C2 | F2: J. de PROYECTO: | G2: =+'Sintesis Economica'!J2
B3: OBRA : | C3: =+'Sintesis Economica'!C3 | F3: Elaboró: | G3: =+'Sintesis Economica'!J3
B4: PLIEGO / E.T.P.: | C4: =+'Sintesis Economica'!C5 | F4: Revisó: | G4: =+'Sintesis Economica'!J4
B5: OFERTA N°: | C5: =+'Sintesis Economica'!C6 | F5: Fecha: | G5: =+'Sintesis Economica'!J5 | J5: =800*41
A7: DOTACIÓN | D7: =SUM('1 MANO DE OBRA'!C15:C20) | E7: COSTOS TOTALES | F7: COSTOS UNITARIOS | G7: % DE DISTRIBUCIÓN
A9: ITEMS | E9: =E11+E19+E25+E33+E40+E48 | F9: =E9/$D$7 | G9: =+SUM(G11:G48)
A11: 1- MANO DE OBRA | E11: =SUM(E12:E15) | F11: =E11/$D$7 | G11: =E11/$E$9 | I11: =+(I12-I13)*0 | J11: COSTO NO CUBIERTO
C12: 1.1 Directa (Personal de Convenio) | E12: ='1 MANO DE OBRA'!L24 | I12: =2700*2.1/(6*187) | J12: COSTO SUPERVISOR ADICIONALES
C13: 1.2 Indirecta (Personal fuera de Convenio) | E13: ='1 MANO DE OBRA'!L36 | I13: =+E13/D7*15% | J13: COSTO MO SUPERVISION PONDERADA
B14: 1 | C14: 1.3 Cobertura de licencias (Horas-Hombre) | E14: =+D14*$E$17
C15: 1.4 Mano de Obra Eventual
C17: COSTO HORA HOMBRE DE REFERENCIA P/COBERTURA DE LICENCIAS | E17: 25
A19: 2- SUMINISTRO DE MATERIALES | E19: =SUM(E20:E23) | F19: =E19/$D$7 | G19: =E19/$E$9
C20: 2.1 Materiales Mecánicos | E20: ='2 SUMINISTRO DE MATERIALES'!G20
C21: 2.2 Materiales Eléctricos | E21: ='2 SUMINISTRO DE MATERIALES'!G33
C22: 2.3 Materiales de Automación e Informática | E22: ='2 SUMINISTRO DE MATERIALES'!G39
C23: 2.4 Materiales Diversos | E23: ='2 SUMINISTRO DE MATERIALES'!G51
A25: 3- SUMINISTRO DE INSUMOS | E25: =SUM(E26:E31) | F25: =E25/$D$7 | G25: =E25/$E$9
C26: 3.1 Insumos consumibles (Insumos de Mantenimto y operación) | E26: ='3 SUMINISTRO DE INSUMOS'!F39 | I26: =+(E26+E30)/D7 | J26: COSTO DE INSUMOS+EPP
C27: 3.2 Combustibles, filtros y lubricantes de Rodados y Máquinas | E27: ='3 SUMINISTRO DE INSUMOS'!F54
C28: 3.3 Insumos informáticos y de Oficina | E28: ='3 SUMINISTRO DE INSUMOS'!F61
C29: 3.4 Insumos de Limpieza y Cafetería | E29: ='3 SUMINISTRO DE INSUMOS'!F68
C30: 3.5 Elementos de Protección Personal y de Seguridad Especiales | E30: ='3 SUMINISTRO DE INSUMOS'!F87
C31: 3.6 Insumos Diversos | E31: ='3 SUMINISTRO DE INSUMOS'!F96
A33: 4- SUBCONTRATACIONES | E33: =SUM(E34:E38) | F33: =E33/$D$7 | G33: =E33/$E$9
C34: 4.1 Honorarios Profesionales | E34: =+'4 SUBCONTRATACIONES'!F26
C35: 4.2 Servicios Técnicos Especializados | E35: =+'4 SUBCONTRATACIONES'!F47
C36: 4.3 Transportes, Fletes, Carga y descarga | E36: =+'4 SUBCONTRATACIONES'!F68
C37: 4.4 Trabajos ejecutados por Terceros | E37: =+'4 SUBCONTRATACIONES'!F89
C38: 4.5 Servicio Varios / Otros | E38: =+'4 SUBCONTRATACIONES'!F110
A40: 5- AMORTIZACIONES | E40: =SUM(E41:E46) | F40: =E40/$D$7 | G40: =E40/$E$9
C41: 5.1 Amortizacion de Rodados | E41: =+'5 AMORTIZACIÓN'!K10
C42: 5.2 Amortización de Muebles y Útiles | E42: =+'5 AMORTIZACIÓN'!K23
C43: 5.3 Amortización de Instalaciones y adecuación de locales | E43: =+'5 AMORTIZACIÓN'!K36
C44: 5.4 Amortización de Medios Informáticos y de Comunicación | E44: =+'5 AMORTIZACIÓN'!K49
C45: 5.5 Amortización de Máquinas y Herramientas | E45: =+'5 AMORTIZACIÓN'!K62 | I45: =+E45/D7*20% | J45: COSTO AMORT. HTAS PONDERADO
C46: 5.6 Amortización de Gastos de Implementación | E46: =+'5 AMORTIZACIÓN'!K75
A48: 6- GASTOS GENERALES | E48: =E50+E55+E61+E67+E73+E80+E88 | F48: =E48/$D$7 | G48: =E48/$E$9
B50: 6.1 Servicios | E50: =SUM(E51:E53) | J50: TELEFONIA MOVIL NEXTEL
C51: 6.1.1 Servicio de Correos y Bolsas | E51: 0 | J51: TELEFONIA MOVIL | K51: APARATOS | L51: =70+15+5+3 | M51: ABONO | N51: =+L51*J51 | O51: SOLO RADIO
C52: 6.1.2 Servicio de Telecomunicación | E52: =(0)+N55+N56 | K52: APARATOS | L52: =90+25+5+3 | M52: ABONO | N52: =+L52*J52 | O52: 400 min
C53: 6.1.3 Servicios esenciales (Electricidad, Agua y Gas) | J53: 4 | K53: APARATOS | L53: 25000 | M53: ABONO | N53: =+L53*J53 | O53: 200 min
B55: 6.2 Alquileres y Leassing | E55: =SUM(E56:E59) | N55: =+SUM(N51:N53)
C56: 6.2.1 Locales | E56: 0 | K56: ALQUILER DE APARATOS PROM MES | N56: 60
C57: 6.2.2 Máquinas y equipos | E57: 0
C58: 6.2.3 Rodados | E58: 0
C59: 6.2.4 Fotocopiadora, fax y medios de Comunicación | E59: 0
B61: 6.3 Mantenimiento | E61: =SUM(E62:E65)
C62: 6.3.1 Repuestos de Máquinas y Equipos Propios | D62: 0.02 | E62: =+'5 AMORTIZACIÓN'!F62/12*D62
C63: 6.3.2 Mantenimiento y Refacción de Locales | D63: 0.03 | E63: =+'5 AMORTIZACIÓN'!F36/12*D63
C64: 6.3.3 Mantenimiento Informático | D64: 0.05 | E64: =+'5 AMORTIZACIÓN'!F49/12*D64
C65: 6.3.4 Mantenimiento de Rodados | D65: 0.03 | E65: =+'5 AMORTIZACIÓN'!F10/12*D65
B67: 6.4 Previsiones Operativas | E67: =SUM(E68:E71)
C68: 6.4.1 Reposición de Medios en Comodato
C69: 6.4.2 Reposición de Herramientas y Medios Propios | D69: 0.03 | E69: ='5 AMORTIZACIÓN'!$F$62*D69/12
C70: 6.4.3 Previsión por Multas y Penalizaciones | D70: 0 | E70: =(E11+E19+E25+E33+E40)*1.1*D70
C71: 6.4.4 Otras Previsiones - Imprevistos | D71: 0 | E71: =+(E11+E19+E25+E33)*D71
B73: 6.5 Seguros | E73: =SUM(E74:E78)
C74: 6.5.1 Seguros de Rodados | E74: 0 | I74: 30000
C75: 6.5.2 Seguro de Responsabilidad Civil | D75: =+E75/$E$9 | E75: =+I75/12/2 | I75: 0 | J75: POLIZA ANUAL POR $1.000.000
C76: 6.5.3 Seguro de Caución | E76: =+I76
C77: 6.5.4 Seguro de Máquinas, muebles y útiles | E77: 0
C78: 6.5.5 Otras coberturas de Seguro | E78: 0
B80: 6.6 Otros Gastos Generales | E80: =SUM(E81:E86)
C81: 6.6.1 Impuesto a los sellos | E81: 0
C82: 6.6.2 Garantia de adjudicación | E82: 0
C83: 6.6.3 Fondo de Reparo | E83: 0
C84: 6.6.4 Costo financiero | D84: 0 | E84: =+I84*D84*J84/(12*'Hoja de CIERRE'!AD45)
C85: 6.6.5 Gastos de Rte. Técnico, o Entes Gubernamentales | E85: 0 | F85: APOYO SINDOICATO
C86: 6.6.6 Otros Gastos Generales (COSTO ESTRUCTURA + IVA RETENIDO) | E86: =0+K86
B88: 6.7 Viáticos | E88: =SUM(E89:E92)
C89: 6.7.1 Refrigerios | E89: ='1 MANO DE OBRA'!E53 | J89: TRANSPORTE
C90: 6.7.2 Alojamientos | E90: ='1 MANO DE OBRA'!E58
C91: 6.7.3 Traslados | E91: ='1 MANO DE OBRA'!E63
C92: 6.7.4 Vehiculos | E92: ='1 MANO DE OBRA'!E68
D95: Jefe de Proyecto | F95: R.U.S. / Resp. PROYECTO

Sheet 1 MANO DE OBRA
C1: 1 - MANO DE OBRA
B3: CLIENTE: | C3: ='Sintesis Economica'!C2 | K3: J. de PROYECTO: | L3: ='Sintesis Economica'!J2
B4: OBRA : | C4: ='Sintesis Economica'!C3 | K4: Elaboró: | L4: ='Sintesis Economica'!J3
B5: PLIEGO / E.T.P.Nº: | C5: ='Sintesis Economica'!C5 | K5: Revisó: | L5: ='Sintesis Economica'!J4
B6: OFERTA N°: | C6: ='Sintesis Economica'!C6 | K6: Fecha: | L6: ='Sintesis Economica'!J5
C8: COEF. POR HORAS EXTRAS | G8: 1.5 | H8: 2
D9: 0 | E9: 0
B10: MANO DE OBRA
B11: MANO DE OBRA DIRECTA (UOM + ASMRA) | C11: CANTIDAD HHN | D11: CANTIDAD HH 50% | E11: CANTIDAD HH 100% | F11: Costo Unit. HHN | G11: Costo Unit. HH 50% | H11: Costo Unit. HH 100% | I11: Costo Horas Normales | J11: Costo Horas 50% | K11: Costo Horas 100% | L11: Costo total
G12: =+F12*$G$8 | H12: =+F12*$H$8 | I12: =+C12*F12 | J12: =+D12*G12 | K12: =+E12*H12 | L12: =I12+J12+K12
G13: =+F13*$G$8 | H13: =+F13*$H$8 | I13: =+C13*F13 | J13: =+D13*G13 | K13: =+E13*H13 | L13: =I13+J13+K13
C14: 0 | D14: =+C14*$D$9 | E14: =+C14*$E$9 | F14: =+'COSTO UNIT.MO_UOM_CAT-GRAL'!P84 | G14: =+F14*$G$8 | H14: =+F14*$H$8 | I14: =+C14*F14 | J14: =+D14*G14 | K14: =+E14*H14 | L14: =I14+J14+K14
C15: 0 | D15: =+C15*$D$9 | E15: =+C15*$E$9 | F15: =+'COSTO UNIT.MO_UOM_CAT-GRAL'!N84 | G15: =+F15*$G$8 | H15: =+F15*$H$8 | I15: =+C15*F15 | J15: =+D15*G15 | K15: =+E15*H15 | L15: =I15+J15+K15
C16: 0 | D16: =+C16*$D$9 | E16: =+C16*$E$9 | F16: =+'COSTO UNIT.MO_UOM_CAT-GRAL'!L84 | G16: =+F16*$G$8 | H16: =+F16*$H$8 | I16: =+C16*F16 | J16: =+D16*G16 | K16: =+E16*H16 | L16: =I16+J16+K16
B17: ='COSTO UNIT.MO_UOM_CAT-GRAL'!I13 | C17: 0 | D17: 0 | E17: =+C17*$E$9 | F17: =+'COSTO UNIT.MO_UOM_CAT-GRAL'!J84 | G17: =+F17*$G$8 | H17: =+F17*$H$8 | I17: =+C17*F17 | J17: =+D17*G17 | K17: =+E17*H17 | L17: =I17+J17+K17
B18: ='COSTO UNIT.MO_UOM_CAT-GRAL'!G13 | C18: 0 | D18: 0 | E18: =+C18*$E$9 | F18: =+'COSTO UNIT.MO_UOM_CAT-GRAL'!H84 | G18: =+F18*$G$8 | H18: =+F18*$H$8 | I18: =+C18*F18 | J18: =+D18*G18 | K18: =+E18*H18 | L18: =I18+J18+K18
B19: ='COSTO UNIT.MO_UOM_CAT-GRAL'!E13 | C19: 0 | D19: =+C19*$D$9 | E19: =+C19*$E$9 | F19: =+'COSTO UNIT.MO_UOM_CAT-GRAL'!F84 | G19: =+F19*$G$8 | H19: =+F19*$H$8 | I19: =+C19*F19 | J19: =+D19*G19 | K19: =+E19*H19 | L19: =I19+J19+K19
C20: 0 | G20: =+F20*$G$8 | H20: =+F20*$H$8 | I20: =+C20*F20 | J20: =+D20*G20 | K20: =+E20*H20 | L20: =I20+J20+K20
C21: 0 | G21: =+F21*$G$8 | H21: =+F21*$H$8 | I21: =+C21*F21 | J21: =+D21*G21 | K21: =+E21*H21 | L21: =I21+J21+K21
C22: 0 | G22: =+F22*$G$8 | H22: =+F22*$H$8 | I22: =+C22*F22 | J22: =+D22*G22 | K22: =+E22*H22 | L22: =I22+J22+K22
C23: 0 | I23: =+C23*F23 | J23: =+D23*G23 | K23: =+E23*H23 | L23: =I23+J23+K23
B24: TOTAL ($) MANO DE OBRA DIRECTA | C24: =+SUM(C12:C23) | D24: =+SUM(D12:D23) | E24: =+SUM(E12:E23) | I24: =SUM(I12:I23) | J24: =SUM(J12:J23) | K24: =SUM(K12:K23) | L24: =SUM(L12:L23) | M24: =+I24/C24 | P24: =C24/187
B25: MANO DE OBRA INDIRECTA | C25: Cantidad Horas Normal | D25: Cantidad Horas 50% | E25: Cantidad Horas 100% | F25: Costo Unit. HHN | G25: Costo Unit. HH 50% | H25: Costo Unit. HH 100% | I25: Costo Horas Normales | J25: Costo Horas 50% | K25: Costo Horas 100% | L25: Costo total
B26: =+'COSTO MO FC'!B8 | C26: 0 | D26: =+C26*0% | E26: =+C26*0% | F26: =+'COSTO MO FC'!AJ8 | G26: =+F26*$G$8 | H26: =+F26*$H$8 | I26: =+C26*F26 | J26: =+D26*G26 | K26: =+E26*H26 | L26: =I26+J26+K26
B27: =+'COSTO MO FC'!B9 | C27: 0 | D27: =+C27*0% | E27: =+C27*0% | F27: =+'COSTO MO FC'!AJ9 | G27: =+F27*$G$8 | H27: =+F27*$H$8 | I27: =+C27*F27 | J27: =+D27*G27 | K27: =+E27*H27 | L27: =I27+J27+K27
B28: =+'COSTO MO FC'!B10 | C28: 0 | D28: =+C28*0% | E28: =+C28*0% | F28: =+'COSTO MO FC'!AJ10 | G28: =+F28*$G$8 | H28: =+F28*$H$8 | I28: =+C28*F28 | J28: =+D28*G28 | K28: =+E28*H28 | L28: =I28+J28+K28
B29: =+'COSTO MO FC'!B11 | C29: 0 | D29: =+C29*0% | E29: =+C29*0% | F29: =+'COSTO MO FC'!AJ11 | G29: =+F29*$G$8 | H29: =+F29*$H$8 | I29: =+C29*F29 | J29: =+D29*G29 | K29: =+E29*H29 | L29: =I29+J29+K29
B30: =+'COSTO MO FC'!B12 | C30: 0 | D30: =+C30*0% | E30: =+C30*0% | F30: =+'COSTO MO FC'!AJ12 | G30: =+F30*$G$8 | H30: =+F30*$H$8 | I30: =+C30*F30 | J30: =+D30*G30 | K30: =+E30*H30 | L30: =I30+J30+K30 | N30: =L30/L36
B31: =+'COSTO MO FC'!B13 | C31: 0 | D31: =+C31*0% | E31: =+C31*0% | F31: =+'COSTO MO FC'!AJ13 | G31: =+F31*$G$8 | H31: =+F31*$H$8 | I31: =+C31*F31 | J31: =+D31*G31 | K31: =+E31*H31 | L31: =I31+J31+K31
B32: =+'COSTO MO FC'!B14 | C32: 0 | D32: =+C32*0% | E32: =+C32*0% | F32: =+'COSTO MO FC'!AJ14 | G32: =+F32*$G$8 | H32: =+F32*$H$8 | I32: =+C32*F32 | J32: =+D32*G32 | K32: =+E32*H32 | L32: =I32+J32+K32
B33: =+'COSTO MO FC'!B15 | C33: 0 | D33: =+C33*0% | E33: =+C33*0% | F33: =+'COSTO MO FC'!AJ15 | G33: =+F33*$G$8 | H33: =+F33*$H$8 | I33: =+C33*F33 | L33: =I33+J33+K33
C34: 0 | G34: =+F34*$G$8 | H34: =+F34*$H$8 | I34: =+C34*F34 | L34: =I34+J34+K34
C35: 0 | G35: =+F35*$G$8 | H35: =+F35*$H$8 | I35: =+C35*F35 | J35: =+D35*G35 | K35: =+E35*H35 | L35: =I35+J35+K35
B36: TOTAL ($) MANO DE OBRA INDIRECTA | C36: =+SUM(C26:C35) | D36: =+SUM(D26:D35) | E36: =+SUM(E26:E35) | I36: =SUM(I26:I35) | J36: =SUM(J26:J35) | K36: =SUM(K26:K35) | L36: =SUM(L26:L35)
B37: MANO DE OBRA EVENTUAL | C37: Cantidad Horas Normal | D37: Cantidad Horas 50% | E37: Cantidad Horas 100% | F37: Costo Unit. HHN | G37: Costo Unit. HH 50% | H37: Costo Unit. HH 100% | I37: Costo Horas Normales | J37: Costo Horas 50% | K37: Costo Horas 100% | L37: Costo total
C38: 0 | G38: =+F38*$G$8 | H38: =+F38*$H$8 | I38: =+C38*F38 | J38: =+D38*G38 | K38: =+E38*H38 | L38: =I38+J38+K38
C39: 0 | G39: =+F39*$G$8 | H39: =+F39*$H$8 | I39: =+C39*F39 | J39: =+D39*G39 | K39: =+E39*H39 | L39: =I39+J39+K39
C40: 0 | G40: =+F40*$G$8 | H40: =+F40*$H$8 | I40: =+C40*F40 | J40: =+D40*G40 | K40: =+E40*H40 | L40: =I40+J40+K40
C41: 0 | G41: =+F41*$G$8 | H41: =+F41*$H$8 | I41: =+C41*F41 | J41: =+D41*G41 | K41: =+E41*H41 | L41: =I41+J41+K41
B42: TOTAL ($) MANO DE OBRA EVENTUAL | C42: =+SUM(C38:C41) | D42: =+SUM(D38:D41) | E42: =+SUM(E38:E41) | I42: =SUM(I38:I41) | J42: =SUM(J38:J41) | K42: =SUM(K38:K41) | L42: =SUM(L38:L41)
B43: TOTAL ($) MANO DE OBRA | I43: =I36+I24+I42 | J43: =J36+J24+J42 | K43: =K36+K24+K42 | L43: =L36+L24+L42
B44: CANTIDAD DE HH NORMALES TOTALES | L44: =+C24+C36+C42
B45: CANTIDAD DE HOMBRE | L45: =+L44/187
B47: VIATICOS
B48: REFIRGERIOS | C48: Precio Unitario ($) | D48: Cantidad por item | E48: Total / Item ($)
B49: Comida en planta - ALMUERZO | E49: =C49*D49
B50: Comida en planta - REFRIGERIO | E50: =C50*D50
B51: Cena fuera de planta | E51: =C51*D51
B52: Propina | E52: =C52*D52
B53: TOTAL REFRIGERIOS ($) | E53: =SUM(E49:E52)
B54: ALOJAMIENTO | C54: Precio Unitario ($) | D54: Cantidad por item | E54: Total / Item ($)
B55: Hotel | E55: =C55*D55
B56: Telefono | E56: =C56*D56
B57: Lava ropa | E57: =C57*D57
B58: TOTAL ALOJAMIENTOS ($) | E58: =SUM(E55:E57)
B59: TRASLADOS (VIAJES) | C59: Precio Unitario ($) | D59: Cantidad por item | E59: Total / Item ($)
B60: Avion/bus/tren/metro/barco (Ida/Vuelta) | E60: =C60*D60
B61: Transporte del personal Operativo | E61: =C61*D61
B62: Taxis/Remis | E62: =C62*D62
B63: TOTAL TRASLADOS ($) | E63: =SUM(E60:E62)
B64: VEHICULO | C64: Precio ($) | D64: Cantidad por item | E64: Total / Item ($)
B65: Alquiler de vehiculo | E65: =C65*D65
B66: Combustible | E66: =C66*D66
B67: Peajes | E67: =C67*D67
B68: TOTAL VEHICULO ($) | E68: =+SUM(E65:E67)
B69: TOTAL ($) VIATICOS | E69: =+E68+E63+E58+E53

Sheet COSTO UNIT.MO_UOM_CAT-GRAL
A1: APERTURA DE COSTOS
A2: MOA U.O.M. - CATEGORIAS GENERALES
A4: TP=25%
A5: Adicional acería=25%
A6: Calorias=10%
A7: Insalubre=3%
D9: vigencia
A10: VALOR DE CATEGORIA | D10: 46174 | E10: =G10*1.1 | G10: 5703
B12: =SUM(E16:E22) | E12: ESPECIALIDAD EN HORAS NORMALES
A13: 1) MANO DE OBRA | B13: =B12*0.805 | E13: OFICIAL ESPACIALIZADO | G13: OFICIAL | I13: MEDIO OFICIAL | K13: AYUDANTE | M13: ='1 MANO DE OBRA'!$B15 | O13: ='1 MANO DE OBRA'!$B14
B14: =B13*1.7 | E14: $/mes | F14: $/H | G14: $/mes | H14: $/H | I14: $/mes | J14: $/H | K14: $/mes | L14: $/H | M14: $/mes | N14: $/H | O14: $/mes | P14: $/H | Q14: $/mes | R14: $/H | S14: $/mes | T14: $/H
A15: Concepto | D15: VALOR - % | E15: Sueldo Bruto | G15: Sueldo Bruto | I15: Sueldo Bruto | K15: Sueldo Bruto | M15: Sueldo Bruto | O15: Sueldo Bruto | Q15: Sueldo Bruto | S15: Sueldo Bruto
A16: ** Sueldo Básico (CATEGORIA) | E16: =E10*187 | G16: =G10*187 | I16: =I10*187 | K16: =+K10*$C$87 | M16: =+M10*$C$87 | O16: =+O10*$C$87 | Q16: =+Q10*$C$87 | S16: =+S10*$C$87 | T16: =+S16+S20+S21+S22+S25+S29
A17: ** vales alimentarios a remunerativos
A18: ** Electromecanico | M18: =$D$18*M16 | O18: =$D$18*O16
A19: ** Antigüedad | D19: 0 | K19: =K16*$D$19 | M19: =M16*$D$19 | O19: =O16*$D$19 | Q19: =+(Q16+Q17+Q20+Q21+Q22+Q25)*$D$19*$C$19 | S19: =+(S16+S17+S20+S21+S22+S25)*$D$19*$C$19
A20: ** Presentismo | D20: 0.2 | E20: =D20*E16 | G20: =D20*G16 | I20: =D20*I16 | M20: =M16*$D$20 | O20: =O16*$D$20 | Q20: =+Q16*20%*$D$20 | S20: =$D20*S10
A21: ** Adicional ELECTRICIDAD | E21: =E16*D21 | G21: =G16*F21 | I21: =I16*H21 | K21: =K10*20%*$D21*187 | S21: =+S16*20%*$D$21
A22: ** ADICIONAL ALTURA (10%) | E22: =E16*D22 | G22: =G16*D22 | I22: =I16*D22 | Q22: =+Q16*13%*$D$22 | S22: =$D22*9
A23: ** Adicional Nocturnas | K23: =K$10*13%*$D23*187 | Q23: =+Q17*13%*$D$22 | S23: =S16*10%*$D$23
A24: ** Adicional Polucion | K24: =K$10*33%*$D24*187 | Q24: =+O24 | S24: =+Q24
A25: ** Adicional Aceria | K25: =$D25*237*187 | Q25: =+Q16*20%*$D$25 | S25: =+S16*20%*$D$25
A26: NR MES | Q26: =SUM(Q16:Q25)*$D$26 | S26: =SUM(S16:S25)*$D$26
A27: ** Previsión de rotacion he AL 100%+ fc | E27: =(70%*SUM(E16:E26)+55000)/1.4 | G27: =(70%*SUM(G16:G26)+55000)/1.4
A29: ** ADICIONAL ACINDAR 12% sobre todos los conceptos excepto oras extras | C29: 0.12
B31: Sub - Total | E31: =SUM(E16:E27)+E29 | F31: =E31/$C$87 | G31: =SUM(G16:G27)+G29 | H31: =G31/$C$87 | I31: =SUM(I16:I27)+I29 | J31: =I31/$C$87 | K31: =SUM(K16:K27)+K29 | L31: =K31/$C$87 | M31: =SUM(M16:M27)+M29 | N31: =M31/$C$87 | O31: =SUM(O16:O27)+O29 | P31: =O31/$C$87 | Q31: =SUM(Q16:Q27)+Q29 | R31: =Q31/$C$87 | S31: =SUM(S16:S27)+S29 | T31: =S31/$C$87
J32: =30.16
A34: 2) CARGAS SOCIALES DIRECTAS
A35: Concepto | D35: VALOR - %
A36: ** Sistema Integrado de Jubilac. y Pensiones | D36: 0.090718847 | E36: =+$D$36*E31 | G36: =+$D$36*G31 | I36: =+$D$36*I31 | K36: =+$D$36*K31 | M36: =+$D$36*M31 | O36: =+$D$36*O31 | Q36: =+$D$36*Q31 | S36: =+$D$36*S31
A37: ** Régimen Nacional de Asig. Familiares | D37: 0.0444 | E37: =+$D$37*E31 | G37: =+$D$37*G31 | I37: =+$D$37*I31 | K37: =+$D$37*K31 | M37: =+$D$37*M31 | O37: =+$D$37*O31 | Q37: =+$D$37*Q31 | S37: =+$D$37*S31
A38: ** Fondo Nacional de Empleo | D38: 0.0089 | E38: =+$D$38*E31 | G38: =+$D$38*G31 | I38: =+$D$38*I31 | K38: =+$D$38*K31 | M38: =+$D$38*M31 | O38: =+$D$38*O31 | Q38: =+$D$38*Q31 | S38: =+$D$38*S31
A39: ** Ley 19.032 | D39: 0.015 | E39: =+$D$39*E31 | G39: =+$D$39*G31 | I39: =+$D$39*I31 | K39: =+$D$39*K31 | M39: =+$D$39*M31 | O39: =+$D$39*O31 | Q39: =+$D$39*Q31 | S39: =+$D$39*S31
A40: ** Régimen Nacional de Obras Sociales | D40: 0.055 | E40: =+$D$40*E31 | G40: =+$D$40*G31 | I40: =+$D$40*I31 | K40: =+$D$40*K31 | M40: =+$D$40*M31 | O40: =+$D$40*O31 | Q40: =+$D$40*Q31 | S40: =+$D$40*S31
A41: ** Fondo Solidario de Redistribución - ANNSSAL | B41: 7368 | D41: 0.005 | E41: =+$D$41*E31 | G41: =+$D$41*G31 | I41: =+$D$41*I31 | K41: =+$D$41*K31 | M41: =+$D$41*M31 | O41: =+$D$41*O31 | Q41: =+$D$41*Q31 | S41: =+$D$41*S31
A42: ADICIONAL UOCRA | D42: 0.05 | E42: =$D42*E31 | G42: =$D42*G31 | I42: =$D42*I31 | K42: =$D42*K31 | M42: =$D42*M31 | O42: =$D42*O31 | Q42: =$D42*Q31 | S42: =$D42*S31
A43: ** Contribución tickets POR CUOTA SINDICAL | D43: 0.025 | E43: =+E17/(1-$D$43)-E17 | G43: =+G17/(1-$D$43)-G17 | I43: =+I17/(1-$D$43)-I17 | K43: =+K17/(1-$D$43)-K17 | M43: =+M17/(1-$D$43)-M17 | O43: =+O17/(1-$D$43)-O17 | Q43: =+Q17/(1-$D$43)-Q17 | S43: =+S17/(1-$D$43)-S17
B45: Sub - Total | C45: =+SUM(E36:E41)/E31 | D45: =+E45/$E$31 | E45: =+SUM(E36:E43) | F45: =E45/$C$87 | G45: =+SUM(G36:G43) | H45: =G45/$C$87 | I45: =SUM(I36:I43) | J45: =I45/$C$87 | K45: =SUM(K36:K43) | L45: =K45/$C$87 | M45: =SUM(M36:M43) | N45: =M45/$C$87 | O45: =+SUM(O36:O43) | P45: =O45/$C$87 | Q45: =SUM(Q36:Q43) | R45: =Q45/$C$87 | S45: =SUM(S36:S43) | T45: =S45/$C$87
A47: 3) CARGAS SOCIALES INDIRECTAS
A48: Concepto | D48: VALOR - %
A49: ** Incidencia Sueldo Anual Complementario | D49: 0.0833 | E49: =+$D$49*E31 | G49: =+$D$49*G31 | I49: =+$D$49*I31 | K49: =+$D$49*K31 | M49: =+$D$49*M31 | O49: =+$D$49*O31 | Q49: =+$D$49*Q31 | S49: =+$D$49*S31
A50: ** Contribuciones s/S.A.C. | D50: =+C45 | E50: =+$D$50*E49 | G50: =+$D$50*G49 | I50: =+$D$50*I49 | K50: =+$D$50*K49 | M50: =+$D$50*M49 | O50: =+$D$50*O49 | Q50: =+$D$50*Q49 | S50: =+$D$50*S49
A51: ** Ropa de trabajo (VALOR ANUAL/12) | D51: 0 | E51: =+$D$51 | G51: =+$D$51 | I51: =+E51 | K51: =+E51 | M51: =+E51 | O51: =+$D$51 | Q51: =+O51 | S51: =+O51
A52: ** Incidencia proporc. Vacaciones | D52: =4.67% | E52: =+$D$52*E31 | G52: =+$D$52*G31 | I52: =+$D$52*I31 | K52: =+$D$52*K31 | M52: =+$D$52*M31 | O52: =+$D$52*O31 | Q52: =+$D$52*Q31 | S52: =+$D$52*S31
A53: ** Contribuciones s/Vacaciones | D53: =+D50 | E53: =+$D$53*E52 | G53: =+$D$53*G52 | I53: =+$D$53*I52 | K53: =+$D$53*K52 | M53: =+$D$53*M52 | O53: =+$D$53*O52 | Q53: =+$D$53*Q52 | S53: =+$D$53*S52
A54: ** APORTE SINDICAL | D54: 0 | E54: =+$D$54*E31 | G54: =+$D$54*G31 | I54: =+$D$54*I31 | K54: =+$D$54*K31 | M54: =+$D$54*M31 | O54: =+$D$54*O31 | Q54: =+$D$54*Q31 | S54: =+$D$54*S31
A55: ** Previsión Despido | D55: 0.0833 | E55: =+$D$55*E31 | G55: =+$D$55*G31 | I55: =+$D$55*I31 | K55: =+$D$55*K31 | M55: =+$D$55*M31 | O55: =+$D$55*O31 | Q55: =+$D$55*Q31 | S55: =+$D$55*S31
A56: ** Previsión Ausentismo | D56: 0.05 | E56: =+$D$56*E31 | G56: =+$D$56*G31 | I56: =+$D$56*I31 | K56: =+$D$56*K31 | M56: =+$D$56*M31 | O56: =+$D$56*O31 | Q56: =+$D$56*Q31 | S56: =+$D$56*S31
A57: ** Subsidio Fallecimiento | D57: 0 | E57: =+$D$57*E31 | G57: =+$D$57*G31 | I57: =+$D$57*I31 | K57: =+$D$57*K31 | M57: =+$D$57*M31 | O57: =+$D$57*O31 | Q57: =+$D$57*Q31 | S57: =+$D$57*S31
A58: ** Servicio Medico de Emergencias | D58: 0 | E58: =+$D$58*E31 | G58: =+$D$58*G31 | I58: =+$D$58*I31 | K58: =+$D$58*K31 | M58: =+$D$58*M31 | O58: =+$D$58*O31 | Q58: =+$D$58*Q31 | S58: =+$D$58*S31
A59: ** Examenes de Ingreso y Homologación | D59: 100000 | E59: =+$D$59/12 | G59: =+$D$59/12 | I59: =+$D$59/12 | K59: =+$D$59/12 | M59: =+$D$59/12 | O59: =+$D$59/12 | Q59: =+$D$59/12 | S59: =+$D$59/12
A60: ** Previsión No cobranza | E60: =+$D$60*E31 | G60: =+$D$60*G31 | I60: =+$D$60*I31 | K60: =+$D$60*K31 | M60: =+$D$60*M31 | O60: =+$D$60*O31 | Q60: =+$D$60*Q31 | S60: =+$D$60*S31
A61: ** Capacitación | E61: =+$D$61*E31 | G61: =+$D$61*G31 | I61: =+$D$61*I31 | K61: =+$D$61*K31 | M61: =+$D$61*M31 | O61: =+$D$61*O31 | Q61: =+$D$61*Q31 | S61: =+$D$61*S31
A62: ** Previsión Delegados | D62: 0.02 | E62: =+$D$62*E31 | G62: =+$D$62*G31 | I62: =+$D$62*I31 | K62: =+$D$62*K31 | M62: =+$D$62*M31 | O62: =+$D$62*O31 | Q62: =+$D$62*Q31 | S62: =+$D$62*S31
A63: ** Previsión Atenciones al Personal | B63: =+B62/(E31-E29) | D63: =D59/2 | E63: =+$D$59/12/3 | G63: =+$D$59/12/3 | I63: =+$D$59/12/3 | K63: =+$D$59/12/3 | M63: =+$D$59/12/3 | O63: =+$D$59/12/3 | Q63: =+$D$59/12/3 | S63: =+$D$59/12/3
A64: **SEGURO DE VIDA UOM | D64: 20000 | E64: =+$D$64 | G64: =+$D$64 | I64: =+E64 | K64: =+I64 | M64: =+K64 | O64: =+M64 | Q64: =+O64 | S64: =+Q64
A65: ** Previsión Perdidas Logisticas de la MONO DE OBRA en Operación | D65: 0 | E65: =+$D$65*E31 | G65: =+$D$65*G31 | I65: =+$D$65*I31 | K65: =+$D$65*K31 | M65: =+$D$65*M31 | O65: =+$D$65*O31 | Q65: =+$D$65*Q31 | S65: =+$D$65*S31
B67: Sub - Total | D67: =+E67/$E$31 | E67: =SUM(E49:E65) | F67: =E67/$C$87 | G67: =SUM(G49:G65) | H67: =G67/$C$87 | I67: =SUM(I49:I65) | J67: =I67/$C$87 | K67: =SUM(K49:K65) | L67: =K67/$C$87 | M67: =SUM(M49:M65) | N67: =M67/$C$87 | O67: =SUM(O49:O65) | P67: =O67/$C$87 | Q67: =SUM(Q49:Q65) | R67: =Q67/$C$87 | S67: =SUM(S49:S65) | T67: =S67/$C$87
A69: 4) A.R.T. Y SEGURO DE VIDA OBLIGATORIO
A70: Concepto | D70: VALOR - %
A72: ** Asignación fija ART | D72: 1000 | E72: =+D72 | G72: =+F72 | I72: =+D72 | K72: =+I72 | M72: =+K72 | O72: =+N72 | Q72: =+N72 | S72: =+Q72
A73: ** Asignación variable ART | D73: 0.042 | E73: =+(E31+E49+E52)*$D$73 | G73: =+(G31+G49+G52)*$D$73 | I73: =+(I31+I49+I52)*$D$73 | K73: =+(K31+K49+K52)*$D$73 | M73: =+(M31+M49+M52)*$D$73 | O73: =+(O31+O49+O52)*$D$73 | Q73: =+(Q31+Q49+Q52)*$D$73 | S73: =+(S31+S49+S52)*$D$73
A74: ** Seguro de vida obligatorio | D74: 1000 | E74: =+D74 | G74: =+F74 | I74: =+D74 | K74: =+I74 | M74: =+K74 | O74: =+N74 | Q74: =+N74 | S74: =+Q74
B76: Sub - Total | D76: =+E76/E31 | E76: =SUM(E72:E74) | F76: =E76/$C$87 | G76: =SUM(G72:G74) | H76: =G76/$C$87 | I76: =SUM(I72:I74) | J76: =I76/$C$87 | K76: =SUM(K72:K74) | L76: =K76/$C$87 | M76: =SUM(M72:M74) | N76: =M76/$C$87 | O76: =SUM(O72:O74) | P76: =O76/$C$87 | Q76: =SUM(Q72:Q74) | R76: =Q76/$C$87 | S76: =SUM(S72:S74) | T76: =S76/$C$87
A78: 5) GASTOS DE MOVILIDAD Y REFRIGERIO
A80: ** Trasporte | D80: 0 | F80: =+D80/C87 | H80: =+F80/C87 | J80: =+F80 | L80: =+J80 | N80: =+L80 | P80: =+N80 | R80: =+P80 | T80: =+R80
A81: ** Comida | D81: 0 | F81: =+D81/C87 | H81: =+F81/C87 | J81: =+F81 | L81: =+J81 | N81: =+L81 | P81: =+N81 | R81: =+P81 | T81: =+R81
A84: COSTO FINAL | F84: =+F31+F45+F67+F76+F80+F81 | H84: =+H31+H45+H67+H76+H80+H81 | J84: =+J31+J45+J67+J76+J80+J81 | L84: =+L31+L45+L67+L76+L80+L81 | N84: =+N31+N45+N67+N76+N80+N81 | P84: =+P31+P45+P67+P76+P80+P81 | R84: =+R31+R45+R67+R76+R80+R81 | T84: =+T31+T45+T67+T76+T80+T81
F85: =F84*$C$87/$C$88 | H85: =H84*$C$87/$C$88 | J85: =J84*$C$87/$C$88 | L85: =L84*$C$87/$C$88 | N85: =N84*$C$87/$C$88 | P85: =P84*$C$87/$C$88 | R85: =R84*$C$87/$C$88 | T85: =T84*$C$87/$C$88
F86: =F84/(1-'Presupuesto de VENTA'!$G$14)+'Presupuesto de VENTA'!#REF!+'Presupuesto de VENTA'!#REF! | H86: =H84/(1-'Presupuesto de VENTA'!$G$14)+'Presupuesto de VENTA'!#REF!+'Presupuesto de VENTA'!#REF! | J86: =J84/(1-'Presupuesto de VENTA'!$G$14)+'Presupuesto de VENTA'!#REF!+'Presupuesto de VENTA'!#REF! | L86: =L84/(1-'Presupuesto de VENTA'!$G$14)+'Presupuesto de VENTA'!#REF!+'Presupuesto de VENTA'!#REF! | N86: =N84/(1-'Presupuesto de VENTA'!$G$14)+'Presupuesto de VENTA'!#REF!+'Presupuesto de VENTA'!#REF! | P86: =P84/(1-'Presupuesto de VENTA'!$G$14)+'Presupuesto de VENTA'!#REF!+'Presupuesto de VENTA'!#REF! | T86: =T84/(1-'Presupuesto de VENTA'!$G$14)+'Presupuesto de VENTA'!#REF!+'Presupuesto de VENTA'!#REF!
A87: Base Horaria (HS/MES) | C87: 187
E88: ANALISIS DE SUELDOS DE BOLSILLO | O88: ANALISIS DE SUELDOS DE BOLSILLO
E90: ESPECIALIDAD en HORAS NORMALES | O90: ESPECIALIDAD en HORAS NORMALES
E91: =+E13 | G91: =+G13 | I91: =+I13 | K91: =+K13 | M91: =+M13 | O91: =+O13 | Q91: =+Q13 | S91: =+S13
E92: $/mes | F92: $/H | G92: $/mes | H92: $/H | I92: $/mes | J92: $/H | K92: $/mes | L92: $/H | M92: $/mes | N92: $/H | O92: $/mes | P92: $/H | Q92: $/mes | R92: $/H | S92: $/mes | T92: $/H
A93: SUELDO NETO | E93: =+(E31-E27)*(100-15)% | F93: =+E93/$C$87 | G93: =+(G31-G27)*(100-15)% | H93: =+G93/$C$87 | I93: =+(I31-I27)*(100-15)% | J93: =+I93/$C$87 | K93: =+(K31-K27)*(100-15)% | L93: =+K93/$C$87 | M93: =+(M31-M27)*(100-15)% | N93: =+M93/$C$87 | O93: =+(O31-O27)*(100-15)% | P93: =+O93/$C$87 | Q93: =+(Q31-Q27)*(100-15)% | R93: =+Q93/$C$87 | S93: =+(S31-S27)*(100-15)% | T93: =+S93/$C$87
A94: VALES ALIMENTARIOS (TICKETS) | E94: =+E16*$D$42 | F94: =+E94/$C$87 | G94: =+G16*$D$42 | H94: =+G94/$C$87 | I94: =+I16*$D$42 | J94: =+I94/$C$87 | K94: =+K16*$D$42 | L94: =+K94/$C$87 | M94: =+M16*$D$42 | N94: =+M94/$C$87 | O94: =+O16*$D$42 | P94: =+O94/$C$87 | Q94: =+Q16*$D$42 | R94: =+Q94/$C$87 | S94: =+S16*$D$42 | T94: =+S94/$C$87
A95: DECRETO NO REMUNERATIVO | E95: =+E54 | F95: =+E95/$C$87 | G95: =+G54 | H95: =+G95/$C$87 | I95: =+I54 | J95: =+I95/$C$87 | K95: =+K54 | L95: =+K95/$C$87 | M95: =+M54 | N95: =+M95/$C$87 | O95: =+O54 | P95: =+O95/$C$87 | Q95: =+Q54 | R95: =+Q95/$C$87 | S95: =+S54 | T95: =+S95/$C$87
A97: SUELDO DE BOLSILLO (LIQUIDO) | E97: =+SUM(E93:E95) | F97: =+SUM(F93:F95) | G97: =+SUM(G93:G95) | H97: =+SUM(H93:H95) | I97: =+SUM(I93:I95) | J97: =+SUM(J93:J95) | K97: =+SUM(K93:K95) | L97: =+SUM(L93:L95) | ... T97: =+SUM(T93:T95)
A99: COEFICIENTE DE COSTO (BOSILLO/COSTO) | E99: =+F84/F97 | G99: =+H84/H97 | I99: =+J84/J97 | K99: =+L84/L97 | M99: =+N84/N97 | O99: =+P84/P97 | Q99: =+R84/R97 | S99: =+T84/T97
A102: a) CATEGORIAS Generales, Art.6. | B102: NUEVO ACUERDO DE OCTUBRE 2009 | I102: 39661 | K102: 39508
A103: Operario | I103: 8.96 | J103: 1.32 | K103: 6.04
A104: Operario Calificado | J104: 1.28 | K104: 6.540355
A105: Medio Oficial | I105: 10.47 | J105: 1.28 | K105: 7.0645365
A106: Operario Especializado | J106: 1.28 | K106: 7.5410651
A107: Operario Espdo. Múltiple | J107: 1.28 | K107: 7.981854
A108: Oficial | I108: 12.38 | J108: 1.28 | K108: 8.3392505
A109: Oficial Múltiple | I109: 13.33 | J109: 1.28 | K109: 8.9825641
A110: Oficial Multiple Rotacion | I110: =I109

Sheet COSTO MO FC
B2: APERTURA DE COSTOS
B6: Categoria | C6: BASICO/Incremento | D6: DED.FUNCIONAL | E6: SUELDO BASICO TOTAL (FIJO + PRIMAS) | G6: Antigüedad | H6: SAC | I6: Vacaciones | J6: Bonif. Vacac. | K6: Sub- Total | L6: Cargas | M6: Diferencia Medicina Pre-paga | N6: ART | O6: Vales Alimentarios | P6: Vales Alimentarios SAC | Q6: Cargas Vales Alimentarios | R6: Costo Emisión Ticket | S6: Seg. Oblig. | T6: Transporte | U6: Comedor | V6: Servicio Med. | W6: Ropa+Reposición | X6: Atención al personal | Y6: Costos acreditación Bancaria | Z6: ART Fijo | AA6: Exam. Preing. | AB6: Homolog. Examen | AC6: Aporte Sindical | AD6: Previsión Recategorización | AE6: Previsión Ausentismo | AF6: Previsión Capacitación | AG6: Provision Despido | AH6: Decreto/Adicional | AI6: TOTAL COSTO MES | AJ6: TOTAL COSTO HH | AL6: SALARIO NETO ANTES DE IIGG | AM6: VALES ALIMENTARIOS | AN6: SALARIO VARIABLE | AO6: SALARIO DE BOLSILLO (LIQUIDO) | AQ6: COEFICIENTE (COSTO/BOLSILLO)
G7: 0 | I7: 14 | J7: 0 | L7: 0.22 | N7: 0.042 | O7: 0 | Q7: 0.14 | R7: 0.04 | S7: 1.3 | T7: 0 | U7: 0 | V7: 0 | W7: =((400+400*10%)/12)*0 | X7: 5500 | Y7: 0 | Z7: 0.6 | AA7: 5500 | AB7: 0 | AC7: 0 | AD7: 0 | AE7: 0.05 | AF7: 0.02 | AG7: 0.0833 | AH7: 0 | AJ7: 200
B8: ADMINITRADOR DE CONTRATO | C8: =599000*1.4*2.6*1.2 | D8: 1000 | E8: =+C8+D8 | G8: =+((C8+D8)*$G$7) | H8: =(C8+D8+G8)/12 | I8: =((SUM(C8:G8)/25)*$I$7)/12 | J8: =((C8/191)*$J$7)/12 | K8: =+E8+SUM(G8:J8) | L8: =K8*$L$7 | N8: =K8*$N$7 | O8: =(C8)*$O$7 | P8: =O8/12 | Q8: =(O8+P8)*$Q$7 | R8: =(O8+P8)*$R$7 | S8: =+$S$7 | U8: =+$U$7 | V8: =+$V$7 | W8: =+$W$7 | X8: =+$X$7/12 | Y8: =(K8*85%)*$Y$7 | Z8: =+$Z$7 | AA8: =+$AA$7/12 | AB8: =+$AB$7/12 | AC8: =K8*$AC$7 | AD8: =K8*$AD$7 | AE8: =K8*$AE$7 | AF8: =+K8*$AF$7 | AG8: =K8*$AG$7+SUM(C8:D8)*(1/(12*2)) | AH8: =+$AH$7 | AI8: =+SUM(K8:AH8) | AJ8: =+AI8/$AJ$7 | AL8: =+((C8)-(C8)*17%) | AM8: =+O8 | AN8: =+D8-D8*17% | AO8: =+AL8+AM8+AN8 | AQ8: =+AI8/AO8
B9: JEFE DE S&SO, MA y CALIDAD | C9: =1.4*450000*2*1.5 | D9: 1000 | E9: =+C9+D9 | G9: =+((C9+D9)*$G$7) | H9: =(C9+D9+G9)/12 | I9: =((SUM(C9:G9)/25)*$I$7)/12 | J9: =((C9/191)*$J$7)/12 | K9: =+E9+SUM(G9:J9) | L9: =K9*$L$7 | N9: =K9*$N$7 | O9: =(C9)*$O$7 | P9: =O9/12 | Q9: =(O9+P9)*$Q$7 | R9: =(O9+P9)*$R$7 | S9: =+$S$7 | U9: =+$U$7 | V9: =+$V$7 | W9: =+$W$7 | X9: =+$X$7/12 | Y9: =(K9*85%)*$Y$7 | Z9: =+$Z$7 | AA9: =+$AA$7/12 | AB9: =+$AB$7/12 | AC9: =K9*$AC$7 | AD9: =K9*$AD$7 | AE9: =K9*$AE$7 | AF9: =+K9*$AF$7 | AG9: =K9*$AG$7+SUM(C9:D9)*(1/(12*3)) | AH9: =+$AH$7 | AI9: =+SUM(K9:AH9) | AJ9: =+AI9/$AJ$7 | AL9: =+((C9)-(C9)*17%) | AM9: =+O9 | AN9: =+D9-D9*17% | AO9: =+AL9+AM9+AN9 | AQ9: =+AI9/AO9
B10: TECNICOS SEGURIDAD | C10: =1.4*400000*2.5*1.3 | D10: 1000 | E10: =+C10+D10 | G10: =+((C10+D10)*$G$7) | H10: =(C10+D10+G10)/12 | I10: =((SUM(C10:G10)/25)*$I$7)/12 | J10: =((C10/191)*$J$7)/12 | K10: =+E10+SUM(G10:J10) | L10: =K10*$L$7 | N10: =K10*$N$7 | O10: =(C10)*$O$7 | P10: =O10/12 | Q10: =(O10+P10)*$Q$7 | R10: =(O10+P10)*$R$7 | S10: =+$S$7 | U10: =+$U$7 | V10: =+$V$7 | W10: =+$W$7 | X10: =+$X$7/12 | Y10: =(K10*85%)*$Y$7 | Z10: =+$Z$7 | AA10: =+$AA$7/12 | AB10: =+$AB$7/12 | AC10: =K10*$AC$7 | AD10: =K10*$AD$7 | AE10: =K10*$AE$7 | AF10: =+K10*$AF$7 | AG10: =K10*$AG$7+SUM(C10:D10)*(1/(12*3)) | AH10: =+$AH$7 | AI10: =+SUM(K10:AH10) | AJ10: =+AI10/$AJ$7 | AL10: =+((C10)-(C10)*17%) | AM10: =+O10 | AN10: =+D10-D10*17% | AO10: =+AL10+AM10+AN10 | AQ10: =+AI10/AO10
A11: =15000000/0.83 | B11: SUPERVISOR | C11: =1.4*300000*2*2.2 | D11: 1000 | E11: =+C11+D11 | G11: =+((C11+D11)*$G$7) | H11: =(C11+D11+G11)/12 | I11: =((SUM(C11:G11)/25)*$I$7)/12 | J11: =((C11/191)*$J$7)/12 | K11: =+E11+SUM(G11:J11) | L11: =K11*$L$7 | N11: =K11*$N$7 | O11: =(C11)*$O$7 | P11: =O11/12 | Q11: =(O11+P11)*$Q$7 | R11: =(O11+P11)*$R$7 | S11: =+$S$7 | U11: =+$U$7 | V11: =+$V$7 | W11: =+$W$7 | X11: =+$X$7/12 | Y11: =(K11*85%)*$Y$7 | Z11: =+$Z$7 | AA11: =+$AA$7/12 | AB11: =+$AB$7/12 | AC11: =K11*$AC$7 | AD11: =K11*$AD$7 | AE11: =K11*$AE$7 | AF11: =+K11*$AF$7 | AG11: =K11*$AG$7+SUM(C11:D11)*(1/(12*3)) | AH11: =+$AH$7 | AI11: =+SUM(K11:AH11) | AJ11: =+AI11/$AJ$7 | AL11: =+((C11)-(C11)*17%) | AM11: =+O11 | AN11: =+D11-D11*17% | AO11: =+AL11+AM11+AN11 | AQ11: =+AI11/AO11
B12: ADMINISTRATIVO | C12: =1.4*250000*2*1.5 | D12: 1000 | E12: =+C12+D12 | G12: =+((C12+D12)*$G$7) | H12: =(C12+D12+G12)/12 | I12: =((SUM(C12:G12)/25)*$I$7)/12 | J12: =((C12/191)*$J$7)/12 | K12: =+E12+SUM(G12:J12) | L12: =K12*$L$7 | N12: =K12*$N$7 | O12: =(C12)*$O$7 | P12: =O12/12 | Q12: =(O12+P12)*$Q$7 | R12: =(O12+P12)*$R$7 | S12: =+$S$7 | U12: =+$U$7 | V12: =+$V$7 | W12: =+$W$7 | X12: =+$X$7/12 | Y12: =(K12*85%)*$Y$7 | Z12: =+$Z$7 | AA12: =+$AA$7/12 | AB12: =+$AB$7/12 | AC12: =K12*$AC$7 | AD12: =K12*$AD$7 | AE12: =K12*$AE$7 | AF12: =+K12*$AF$7 | AG12: =K12*$AG$7+SUM(C12:D12)*(1/(12*3)) | AH12: =+$AH$7 | AI12: =+SUM(K12:AH12) | AJ12: =+AI12/$AJ$7 | AL12: =+((C12)-(C12)*17%) | AM12: =+O12 | AN12: =+D12-D12*17% | AO12: =+AL12+AM12+AN12 | AQ12: =+AI12/AO12
B13: PAÑOLERO | C13: =1.4*250000*2*1.5 | D13: 1000 | E13: =+C13+D13 | G13: =+((C13+D13)*$G$7) | H13: =(C13+D13+G13)/12 | I13: =((SUM(C13:G13)/25)*$I$7)/12 | J13: =((C13/191)*$J$7)/12 | K13: =+E13+SUM(G13:J13) | L13: =K13*$L$7 | N13: =K13*$N$7 | O13: =(C13)*$O$7 | P13: =O13/12 | Q13: =(O13+P13)*$Q$7 | R13: =(O13+P13)*$R$7 | S13: =+$S$7 | U13: =+$U$7 | V13: =+$V$7 | W13: =+$W$7 | X13: =+$X$7/12 | Y13: =(K13*85%)*$Y$7 | Z13: =+$Z$7 | AA13: =+$AA$7/12 | AB13: =+$AB$7/12 | AC13: =K13*$AC$7 | AD13: =K13*$AD$7 | AE13: =K13*$AE$7 | AF13: =+K13*$AF$7 | AG13: =K13*$AG$7+SUM(C13:D13)*(1/(12*3)) | AH13: =+$AH$7 | AI13: =+SUM(K13:AH13) | AJ13: =+AI13/$AJ$7 | AL13: =+((C13)-(C13)*17%) | AM13: =+O13 | AN13: =+D13-D13*17% | AO13: =+AL13+AM13+AN13 | AQ13: =+AI13/AO13
B14: CHOFER | C14: =1.4*250000*2*1.5 | D14: 1000 | E14: =+C14+D14 | G14: =+((C14+D14)*$G$7) | H14: =(C14+D14+G14)/12 | I14: =((SUM(C14:G14)/25)*$I$7)/12 | J14: =((C14/191)*$J$7)/12 | K14: =+E14+SUM(G14:J14) | L14: =K14*$L$7 | N14: =K14*$N$7 | O14: =(C14)*$O$7 | P14: =O14/12 | Q14: =(O14+P14)*$Q$7 | R14: =(O14+P14)*$R$7 | S14: =+$S$7 | U14: =+$U$7 | V14: =+$V$7 | W14: =+$W$7 | X14: =+$X$7/12 | Y14: =(K14*85%)*$Y$7 | Z14: =+$Z$7 | AA14: =+$AA$7/12 | AB14: =+$AB$7/12 | AC14: =K14*$AC$7 | AD14: =K14*$AD$7 | AE14: =K14*$AE$7 | AF14: =+K14*$AF$7 | AG14: =K14*$AG$7+SUM(C14:D14)*(1/(12*3)) | AH14: =+$AH$7 | AI14: =+SUM(K14:AH14) | AJ14: =+AI14/$AJ$7 | AL14: =+((C14)-(C14)*17%) | AM14: =+O14 | AN14: =+D14-D14*17% | AO14: =+AL14+AM14+AN14 | AQ14: =+AI14/AO14
B15: LIMPIEZA | C15: =1.4*250000*2*1.5 | D15: 1000 | E15: =+C15+D15 | G15: =+((C15+D15)*$G$7) | H15: =(C15+D15+G15)/12 | I15: =((SUM(C15:G15)/25)*$I$7)/12 | J15: =((C15/191)*$J$7)/12 | K15: =+E15+SUM(G15:J15) | L15: =K15*$L$7 | N15: =K15*$N$7 | O15: =(C15)*$O$7 | P15: =O15/12 | Q15: =(O15+P15)*$Q$7 | R15: =(O15+P15)*$R$7 | S15: =+$S$7 | U15: =+$U$7 | V15: =+$V$7 | W15: =+$W$7 | X15: =+$X$7/12 | Y15: =(K15*85%)*$Y$7 | Z15: =+$Z$7 | AA15: =+$AA$7/12 | AB15: =+$AB$7/12 | AC15: =K15*$AC$7 | AD15: =K15*$AD$7 | AE15: =K15*$AE$7 | AF15: =+K15*$AF$7 | AG15: =K15*$AG$7+SUM(C15:D15)*(1/(12*3)) | AH15: =+$AH$7 | AI15: =+SUM(K15:AH15) | AJ15: =+AI15/$AJ$7 | AL15: =+((C15)-(C15)*17%) | AM15: =+O15 | AN15: =+D15-D15*17% | AO15: =+AL15+AM15+AN15 | AQ15: =+AI15/AO15

Sheet 2 SUMINISTRO DE MATERIALES
C1: 2 - SUMINISTRO DE MATERIALES
B3: CLIENTE: | C3: ='Sintesis Economica'!C2 | F3: J. de PROYECTO: | G3: ='Sintesis Economica'!J2
B4: OBRA : | C4: ='Sintesis Economica'!C3 | F4: Elaboró: | G4: ='Sintesis Economica'!J3
B5: PLIEGO / E.T.P.Nº: | C5: ='Sintesis Economica'!C5 | F5: Revisó: | G5: ='Sintesis Economica'!J4
B6: OFERTA N°: | C6: ='Sintesis Economica'!C6
C7: TOTAL COSTO SUMINISTRO DE MATERIALES | G7: =+G20+G33+G39+G51
B8: 2.1 MATERIALES MECANICOS
B9: ITEM | C9: DESCRIPCION | D9: PRECIO UNITARIO | E9: U | F9: CANT. | G9: COSTO TOTAL
B10: 2.1.1 | D10: 0 | F10: 0 | G10: =+F10*D10
B11: 2.1.2 | D11: 0 | F11: 0 | G11: =+F11*D11
B12: 2.1.3 | D12: 0 | F12: 0 | G12: =+F12*D12
B13: 2.1.4 | D13: 0 | F13: 0 | G13: =+F13*D13
B14: 2.1.5 | D14: 0 | F14: 0 | G14: =+F14*D14
B15: 2.1.6 | D15: 0 | F15: 0 | G15: =+F15*D15
B16: 2.1.7 | D16: 0 | F16: 0 | G16: =+F16*D16
B17: 2.1.8 | D17: 0 | F17: 0 | G17: =+F17*D17
B18: 2.1.9 | D18: 0 | F18: 0 | G18: =+F18*D18
B19: 2.1.10 | D19: 0 | F19: 0 | G19: =+F19*D19
B20: SUBTOTAL MATERIALES MECÁNICOS | G20: =SUM(G10:G19)
C21: 2.2 MATERIALES ELÉCTRICOS
B22: ITEM | C22: DESCRIPCION | D22: PRECIO UNITARIO | E22: U | F22: CANT. | G22: COSTO TOTAL
B23: 2.2.1 | D23: 0 | F23: 0 | G23: =+F23*D23
B24: 2.2.2 | D24: 0 | F24: 0 | G24: =+F24*D24
B25: 2.2.3 | D25: 0 | F25: 0 | G25: =+F25*D25
B26: 2.2.4 | D26: 0 | F26: 0 | G26: =+F26*D26
B27: 2.2.5 | D27: 0 | F27: 0 | G27: =+F27*D27
B28: 2.2.6 | D28: 0 | F28: 0 | G28: =+F28*D28
B29: 2.2.7 | D29: 0 | F29: 0 | G29: =+F29*D29
B30: 2.2.8 | D30: 0 | F30: 0 | G30: =+F30*D30
B31: 2.2.9 | D31: 0 | F31: 0 | G31: =+F31*D31
B32: 2.2.10 | D32: 0 | F32: 0 | G32: =+F32*D32
B33: SUBTOTAL MATERIALES ELECTRICOS | G33: =SUM(G23:G32)
B34: 2.3 MATERIALES AUTOMACION E INFORMATICOS
B35: ITEM | C35: DESCRIPCION | D35: PRECIO UNITARIO | E35: U | F35: CANTIDAD | G35: COSTO TOTAL
B36: 2.3.1 | G36: =+F36*D36
B37: 2.3.2 | G37: =+F37*D37
B38: 2.3.3 | G38: =+F38*D38
B39: SUBTOTAL MATERIALES AUTOMACION E INFORMATICOS | G39: =SUM(G36:G38)
B40: 2.4 MATERIALES DIVERSOS
B41: ITEM | C41: DESCRIPCION | D41: PRECIO UNITARIO | E41: U | F41: CANTIDAD | G41: COSTO TOTAL
B42: 2.4.1 | G42: =+F42*D42
B43: 2.4.2 | G43: =+F43*D43
B44: 2.4.3 | G44: =+F44*D44
B45: 2.4.4 | G45: =+F45*D45
B46: 2.4.5 | G46: =+F46*D46
B47: 2.4.6 | G47: =+F47*D47
B48: 2.4.7 | G48: =+F48*D48
B49: 2.4.8 | G49: =+F49*D49
B50: 2.4.9 | G50: =+F50*D50
B51: SUBTOTAL MATERIALES DIVERSOS | G51: =SUM(G42:G49)

Sheet 3 SUMINISTRO DE INSUMOS
C1: 3- SUMINISTRO DE INSUMOS CONSUMIBLES
B3: CLIENTE: | C3: ='Sintesis Economica'!C2 | E3: J. de PROYECTO: | F3: ='Sintesis Economica'!J2
B4: OBRA : | C4: ='Sintesis Economica'!C3 | E4: Elaboró: | F4: ='Sintesis Economica'!J3
B5: PLIEGO / E.T.P.Nº: | C5: ='Sintesis Economica'!C5 | E5: Revisó: | F5: ='Sintesis Economica'!J4
B6: OFERTA N°: | C6: ='Sintesis Economica'!C6
B7: TOTAL COSTO de INSUMOS CONSUMIBLES | F7: =+F39+F54+F61+F68+F87+F96 | G7: =+F7/#REF!
B8: 3.1 INSUMOS CONSUMIBLES (INSUMOS DIRECTOS DE MANTENIMIENTO Y OPERACIÓN)
B9: ITEM | C9: DESCRIPCION | D9: PRECIO UNITARIO | E9: CANT. | F9: COSTO TOTAL
B10: 3.1.1 | D10: 0 | E10: 0 | F10: =+E10*D10
B11: 3.1.2 | D11: 0 | E11: 0 | F11: =+E11*D11
B12: 3.1.3 | D12: 0 | E12: 0 | F12: =+E12*D12
B13: 3.1.4 | D13: 0 | E13: 0 | F13: =+E13*D13
B14: 3.1.5 | D14: 0 | E14: 0 | F14: =+E14*D14
B15: 3.1.6 | D15: 0 | E15: 0 | F15: =+E15*D15
B16: 3.1.7 | D16: 0 | E16: 0 | F16: =+E16*D16
B17: 3.1.8 | D17: 0 | E17: 0 | F17: =+E17*D17
B18: 3.1.9 | D18: 0 | E18: 0 | F18: =+E18*D18
B19: 3.1.10 | D19: 0 | E19: 0 | F19: =+E19*D19
B20: 3.1.11 | D20: 0 | E20: 0 | F20: =+E20*D20
B21: 3.1.12 | D21: 0 | E21: 0 | F21: =+E21*D21
... B38: 3.1.29 | D38: 0 | E38: 0 | F38: =+E38*D38
B39: SUBTOTAL INSUMOS CONSUMIBLES (INSUMOS DIRECTOS DE MANTENIMIENTO) | F39: =SUM(F10:F38) | G39: =+F39/#REF!
C41: 3.2 COMBUSTIBLE, FILTROS Y LUBRICATES DE RODADOS Y MÁQUINAS
B42: ITEM | C42: DESCRIPCION | D42: PRECIO UNITARIO | E42: CANT. | F42: COSTO TOTAL | I42: CONSUMO DE COMBUSTIBLE | J42: HS/DIA | K42: LTS/HS | L42: DIAS | M42: CTD | N42: TOTAL LTS
B43: 3.2.1 | D43: 0 | E43: 0 | F43: =+E43*D43 | J43: 10 | K43: 1.5 | L43: 22 | M43: 2 | N43: =+J43*K43*L43 | O43: =M43*N43
B44: 3.2.2 | F44: =+E44*D44 | I44: =+'5 AMORTIZACIÓN'!C12 | J44: 10 | K44: 3 | L44: 22 | M44: 2 | N44: =+J44*K44*L44 | O44: =M44*N44
B45: 3.2.3 | F45: =+E45*D45 | I45: =+'5 AMORTIZACIÓN'!C13 | J45: 10 | K45: 3 | L45: 22 | M45: ='5 AMORTIZACIÓN'!E13 | N45: =+J45*K45*L45 | O45: =M45*N45
B46: 3.2.4 | F46: =+E46*D46 | I46: =+'5 AMORTIZACIÓN'!C14 | J46: 10 | K46: 3 | L46: 22 | M46: ='5 AMORTIZACIÓN'!E14 | N46: =+J46*K46*L46 | O46: =M46*N46
B47: 3.2.5 | F47: =+E47*D47 | I47: =+'5 AMORTIZACIÓN'!C15 | J47: 10 | K47: 3 | L47: 22 | M47: ='5 AMORTIZACIÓN'!E15 | N47: =+J47*K47*L47 | O47: =M47*N47
B48: 3.2.6 | F48: =+E48*D48 | I48: =+'5 AMORTIZACIÓN'!C16
B49: 3.2.7 | F49: =+E49*D49
B50: 3.2.8 | F50: =+E50*D50 | M50: =+SUM(M43:M49) | N50: =+SUM(N43:N49) | O50: =+SUM(O43:O49)
B51: 3.2.9 | F51: =+E51*D51
B52: 3.2.10 | F52: =+E52*D52
B53: 3.2.11 | F53: =+E53*D53
B54: SUBTOTAL COMBUSTIBLE, FILTROS Y LUBRICATES | F54: =SUM(F43:F53) | G54: =+F54/#REF!
B56: 3.3 INSUMOS INFORMÁTICOS Y DE OFICINA
B57: ITEM | C57: DESCRIPCION | D57: PRECIO UNITARIO | E57: CANTIDAD | F57: COSTO TOTAL
B58: 3.3.1 | D58: 0 | E58: 0 | F58: =+E58*D58
B59: 3.3.2 | F59: =+E59*D59
B60: 3.3.3 | F60: =+E60*D60
B61: SUBTOTAL INSUMOS INFORMÁTICOS Y DE OFICINA | F61: =SUM(F58:F60) | G61: =+F61/#REF!
B63: 3.4 INSUMOS DE LIMPIEZA Y CAFETERÍA
B64: ITEM | C64: DESCRIPCION | D64: PRECIO UNITARIO | E64: CANTIDAD | F64: COSTO TOTAL
B65: 3.4.1 | D65: 0 | E65: 0 | F65: =+E65*D65
B66: 3.4.2 | F66: =+E66*D66
B67: 3.4.3 | F67: =+E67*D67
B68: SUBTOTAL INSUMOS DE LIMPIEZA Y CAFETERÍA | F68: =SUM(F65:F67) | G68: =+F68/#REF!
C70: 3.5 ELEMENTOS DE SEGURIDAD Y PROTECCIÓN PERSONAL
B71: ITEM | C71: DESCRIPCION | D71: PRECIO UNITARIO | E71: CANT. | F71: COSTO TOTAL
B72: 3.5.1 | D72: 0 | E72: 0 | F72: =+E72*D72 | H72: CANTIDAD DE PERSONAL
B73: 3.5.2 | D73: 0 | E73: 0 | F73: =+E73*D73 | H73: ='1 MANO DE OBRA'!L45 | I73: =H73*80+350*2*H73/12
B74: 3.5.3 | D74: 0 | E74: 0 | F74: =+E74*D74
B75: 3.5.4 | D75: 0 | E75: 0 | F75: =+E75*D75
B76: 3.5.5 | D76: 0 | E76: 0 | F76: =+E76*D76
B77: 3.5.6 | D77: 0 | E77: 0 | F77: =+E77*D77
B78: 3.5.7 | D78: 0 | E78: 0 | F78: =+E78*D78
B79: 3.5.8 | D79: 0 | E79: 0 | F79: =+E79*D79
B80: 3.5.9 | D80: 0 | E80: 0 | F80: =+E80*D80
B81: 3.5.10 | D81: 0 | E81: 0 | F81: =+E81*D81
B82: 3.5.11 | D82: 0 | E82: 0 | F82: =+E82*D82
B83: 3.5.12 | D83: 0 | E83: 0 | F83: =+E83*D83
B84: 3.5.13 | D84: 0 | E84: 0 | F84: =+E84*D84
B85: 3.5.14 | D85: 0 | E85: 0 | F85: =+E85*D85
B86: 3.5.15 | D86: 0 | E86: 0 | F86: =+E86*D86
B87: SUBTOTAL ELEMENTOS DE SEGURIDAD Y PROTECCIÓN PERSONAL | F87: =SUM(F72:F86)
H88: =+F87/#REF!
B89: 3.6 INSUMOS DIVERSOS
B90: ITEM | C90: DESCRIPCION | D90: PRECIO UNITARIO | E90: CANTIDAD | F90: COSTO TOTAL
B91: 3.6.1 | F91: =+E91*D91 | H91: 0
B92: 3.6.2 | F92: =+E92*D92
B93: 3.6.3 | F93: =+E93*D93
B94: 3.6.4 | F94: =+E94*D94
B95: 3.6.5 | F95: =+E95*D95
B96: SUBTOTAL INSUMOS DIVERSOS | F96: =SUM(F91:F95)

Sheet 4 SUBCONTRATACIONES
B1: 4 - SUBCONTRATACIONES
B3: CLIENTE: | C3: ='Sintesis Economica'!C2 | E3: J. de PROYECTO: | F3: ='Sintesis Economica'!J2
B4: OBRA : | C4: ='Sintesis Economica'!C3 | E4: Elaboró: | F4: ='Sintesis Economica'!J3
B5: PLIEGO / E.T.P.Nº: | C5: ='Sintesis Economica'!C5 | E5: Revisó: | F5: ='Sintesis Economica'!J4
B6: OFERTA N°: | C6: ='Sintesis Economica'!C6
B7: TOTAL COSTO DE SUBCONTRATACIONES | F7: =+F26+F47+F68+F89+F110
B8: 4.1 HONORARIOS PROFESIONALES
B9: ITEM | C9: DESCRIPCION | D9: PRECIO UNITARIO | E9: CANT. | F9: COSTO TOTAL
B10: 4.1.1 | D10: 0 | E10: 0 | F10: =+E10*D10
B11: 4.1.2 | D11: 0 | E11: 0 | F11: =+E11*D11
B12: 4.1.3 | D12: 0 | E12: 0 | F12: =+E12*D12
B13: 4.1.4 | D13: 0 | E13: 0 | F13: =+E13*D13
B14: 4.1.5 | D14: 0 | E14: 0 | F14: =+E14*D14
B15: 4.1.6 | D15: 0 | E15: 0 | F15: =+E15*D15
B16: 4.1.7 | D16: 0 | E16: 0 | F16: =+E16*D16
B17: 4.1.8 | D17: 0 | E17: 0 | F17: =+E17*D17
B18: 4.1.9 | D18: 0 | E18: 0 | F18: =+E18*D18
B19: 4.1.10 | D19: 0 | E19: 0 | F19: =+E19*D19
B20: 4.1.11 | D20: 0 | E20: 0 | F20: =+E20*D20
B21: 4.1.12 | D21: 0 | E21: 0 | F21: =+E21*D21
... B25: 4.1.16 | D25: 0 | E25: 0 | F25: =+E25*D25
B26: SUBTOTAL HONORARIOS PROFESIONALES | F26: =SUM(F10:F25)
B29: 4.2 SERVICIOS TECNICOS ESPECIALIZADOS
B30: ITEM | C30: DESCRIPCION | D30: PRECIO UNITARIO | E30: CANT. | F30: COSTO TOTAL
B31: 4.2.1 | F31: =+E31*D31 | G31: 0
B32: 4.2.2 | F32: =+E32*D32
B33: 4.2.3 | F33: =+E33*D33
B34: 4.2.4 | F34: =+E34*D34
B35: 4.2.5 | F35: =+E35*D35
B36: 4.2.6 | F36: =+E36*D36
B37: 4.2.7 | F37: =+E37*D37
B38: 4.2.8 | F38: =+E38*D38
B39: 4.2.9 | F39: =+E39*D39
B40: 4.2.10 | F40: =+E40*D40
B41: 4.2.11 | F41: =+E41*D41
B42: 4.2.12 | F42: =+E42*D42
B43: 4.2.13 | F43: =+E43*D43
... B46: 4.2.16 | F46: =+E46*D46
B47: SUBTOTAL SERVICIOS TECNICOS ESPECIALIZADOS | F47: =SUM(F31:F46)
B50: 4.3 TRANSPORTES, FLESTES, CARGAS Y DESCARGAS
B51: ITEM | C51: DESCRIPCION | D51: PRECIO UNITARIO | E51: CANT. | F51: COSTO TOTAL
B52: 4.3.1 | F52: =+E52*D52
B53: 4.3.2 | F53: =+E53*D53
B54: 4.3.3 | F54: =+E54*D54
B55: 4.3.4 | F55: =+E55*D55
B56: 4.3.5 | F56: =+E56*D56
B57: 4.3.6 | F57: =+E57*D57
B58: 4.3.7 | F58: =+E58*D58
B59: 4.3.8 | F59: =+E59*D59
B60: 4.3.9 | F60: =+E60*D60
B61: 4.3.10 | F61: =+E61*D61
B62: 4.3.11 | F62: =+E62*D62
B63: 4.3.12 | F63: =+E63*D63
... B67: 4.3.16 | F67: =+E67*D67
B68: SUBTOTAL TRASNPORTE Y FLETES | F68: =SUM(F52:F67)
B71: 4.4 TRABAJOS EJECUTADOS POR TERCEROS
B72: ITEM | C72: DESCRIPCION | D72: PRECIO UNITARIO | E72: CANT. | F72: COSTO TOTAL
B73: 4.4.1 | F73: =+E73*D73
B74: 4.4.2 | F74: =+E74*D74
B75: 4.4.3 | F75: =+E75*D75
B76: 4.4.4 | F76: =+E76*D76
B77: 4.4.5 | F77: =+E77*D77
B78: 4.4.6 | F78: =+E78*D78
B79: 4.4.7 | F79: =+E79*D79
B80: 4.4.8 | F80: =+E80*D80
B81: 4.4.9 | F81: =+E81*D81
B82: 4.4.10 | F82: =+E82*D82
B83: 4.4.11 | F83: =+E83*D83
B84: 4.4.12 | F84: =+E84*D84
... B88: 4.4.16 | F88: =+E88*D88
B89: SUBTOTAL TRABAJOS EJECUTADOS POR TERCEROS | F89: =SUM(F73:F88)
B92: 4.5 SERVICIOS VARIOS / OTROS
B93: ITEM | C93: DESCRIPCION | D93: PRECIO UNITARIO | E93: CANT. | F93: COSTO TOTAL
B94: 4.5.1 | F94: =+E94*D94 | G94: 0
B95: 4.5.2 | F95: =+E95*D95
B96: 4.5.3 | F96: =+E96*D96
B97: 4.5.4 | F97: =+E97*D97
B98: 4.5.5 | F98: =+E98*D98
B99: 4.5.6 | F99: =+E99*D99
B100: 4.5.7 | F100: =+E100*D100
B101: 4.5.8 | F101: =+E101*D101
B102: 4.5.9 | F102: =+E102*D102
B103: 4.5.10 | F103: =+E103*D103
B104: 4.5.11 | F104: =+E104*D104
B105: 4.5.12 | F105: =+E105*D105
B106: 4.5.13 | F106: =+E106*D106
... B109: 4.5.16 | F109: =+E109*D109
B110: SUBTOTAL SERVICIOS VARIOS | F110: =SUM(F94:F109)
B115: ADICIONAL MTO. CORRECTIVO PROGRAMADO MAYOR CON PEGAMENTOS | R115: =+T117
C117: 3.5 | D117: Ho | E117: 8 | F117: Hs | G117: 3 | H117: turnos | I117: 3 | J117: dias | K117: 4 | L117: veces | M117: 32 | N117: $/HH | O117: 1 | P117: Coef. | Q117: = | R117: =+C117*E117*G117*I117*K117*M117*O117 | S117: 36 | T117: =+R122/S117
C118: =+C117 | D118: Ho | E118: 2 | F118: Hs | G118: 3 | H118: turnos | I118: 3 | J118: dias | K118: 4 | L118: veces | M118: 32 | N118: $/HH | O118: 1.38 | P118: Coef. | Q118: = | R118: =+C118*E118*G118*I118*K118*M118*O118
C119: =+C118 | D119: Ho | E119: 2 | F119: Hs | G119: 3 | H119: turnos | I119: 3 | J119: dias | K119: 4 | L119: veces | M119: 32 | N119: $/HH | O119: 1.76 | P119: Coef. | Q119: = | R119: =+C119*E119*G119*I119*K119*M119*O119
K120: 36 | L120: veces | M120: 12000 | N120: Materiales | Q120: = | R120: =+M120*K120
R122: =+SUM(R117:R120)
R123: =+R122-D73

Sheet 5 AMORTIZACIÓN
B1: 5- MONTO DE INVERSIÓN Y CÁLCULO DE AMORTIZACIÓN MENSUAL
B3: CLIENTE: | C3: ='Sintesis Economica'!C2
B4: OBRA : | C4: ='Sintesis Economica'!C3 | I4: Jefe de Proyecto: | J4: ='Sintesis Economica'!J2
B5: PLIEGO / E.T.P.Nº: | C5: ='Sintesis Economica'!C5 | I5: Elaboró: | J5: ='Sintesis Economica'!J3
B6: OFERTA N°: | C6: ='Sintesis Economica'!C6 | I6: Revisó: | J6: ='Sintesis Economica'!J4
B8: TOTAL MENSUAL AMORTIZABLE | J8: =(K10+K23+K36+K49+K62+K75)
B9: ITEM | C9: Descripción | D9: Costo Unit. | E9: Cant. | F9: Inversión | G9: Plazo de amortización (en años) | H9: Valor Residual | J9: Costo Financiero | K9: AMORTIZACIÓN MENSUAL
B10: 5.1 | C10: RODADOS Y EQUIPOS MOVILES ESPECIALES | F10: =SUM(F11:F22) | I10: =SUM(I11:I22) | J10: 0.02 | K10: =SUM(K11:K22)*-1
B11: 5.1.1 | D11: 0 | E11: 0 | F11: =+D11*E11 | G11: 5 | H11: 0.5 | I11: =+F11*H11 | J11: =+$J$10 | K11: =PMT(J11,G11*12,F11-I11,0)-I11*J11
B12: 5.1.2 | D12: 0 | E12: 0 | F12: =+D12*E12 | G12: 5 | H12: 0.5 | I12: =+F12*H12 | J12: =+$J$10 | K12: =PMT(J12,G12*12,F12-I12,0)-I12*J12
B13: 5.1.3 | D13: 0 | E13: 0 | F13: =+D13*E13 | G13: 5 | H13: 0.5 | I13: =+F13*H13 | J13: =+$J$10 | K13: =PMT(J13,G13*12,F13-I13,0)-I13*J13
B14: 5.1.4 | D14: 0 | E14: 0 | F14: =+D14*E14 | G14: 5 | H14: 0.4 | I14: =+F14*H14 | J14: =+$J$10 | K14: =PMT(J14,G14*12,F14-I14,0)-I14*J14
B15: 5.1.5 | D15: 0 | E15: 0 | F15: =+D15*E15 | G15: 5 | H15: 0.4 | I15: =+F15*H15 | J15: =+$J$10 | K15: =PMT(J15,G15*12,F15-I15,0)-I15*J15
B16: 5.1.6 | D16: 0 | E16: 0 | F16: =+D16*E16 | G16: 5 | H16: 0.4 | I16: =+F16*H16 | J16: =+$J$10 | K16: =PMT(J16,G16*12,F16-I16,0)-I16*J16
B17: 5.1.7 | D17: 0 | E17: 0 | F17: =+D17*E17 | G17: 3 | H17: 0.4 | I17: =+F17*H17 | J17: =+$J$10 | K17: =PMT(J17,G17*12,F17-I17,0)-I17*J17
B18: 5.1.8 | D18: 0 | E18: 0 | F18: =+D18*E18 | G18: 3 | H18: 0 | I18: =+F18*H18 | J18: =+$J$10 | K18: =PMT(J18,G18*12,F18-I18,0)-I18*J18
B19: 5.1.9 | D19: 0 | E19: 0 | F19: =+D19*E19 | G19: 3 | H19: 0 | I19: =+F19*H19 | J19: =+$J$10 | K19: =PMT(J19,G19*12,F19-I19,0)-I19*J19
B20: 5.1.10 | D20: 0 | E20: 0 | F20: =+D20*E20 | G20: 3 | H20: 0.3 | I20: =+F20*H20 | J20: =+$J$10 | K20: =PMT(J20,G20*12,F20-I20,0)-I20*J20
B21: 5.1.11 | D21: 0 | E21: 0 | F21: =+D21*E21 | G21: 3 | H21: 0 | I21: =+F21*H21 | J21: =+$J$10 | K21: =PMT(J21,G21*12,F21-I21,0)-I21*J21
B22: 5.1.12 | D22: 0 | E22: 0 | F22: =+D22*E22 | G22: 3 | H22: 0 | I22: =+F22*H22 | J22: =+$J$10 | K22: =PMT(J22,G22*12,F22-I22,0)-I22*J22
B23: 5.2 | C23: MUEBLES Y ÚTILES | F23: =SUM(F24:F35) | I23: =SUM(I24:I35) | K23: =SUM(K24:K35)*-1
B24: 5.2.1 | D24: 0 | E24: 0 | F24: =+D24*E24 | G24: 1 | H24: 0 | I24: =+F24*H24 | J24: =+$J$10 | K24: =PMT(J24,G24*12,F24-I24,0)-I24*J24
B25: 5.2.2 | D25: 0 | E25: 0 | F25: =+D25*E25 | G25: 8 | H25: 0.8 | I25: =+F25*H25 | J25: =+$J$10 | K25: =PMT(J25,G25*12,F25-I25,0)-I25*J25
B26: 5.2.3 | D26: 0 | E26: 0 | F26: =+D26*E26 | G26: 3 | H26: 0 | I26: =+F26*H26 | J26: =+$J$10 | K26: =PMT(J26,G26*12,F26-I26,0)-I26*J26
B27: 5.2.4 | D27: 0 | E27: 0 | F27: =+D27*E27 | G27: 3 | H27: 0 | I27: =+F27*H27 | J27: =+$J$10 | K27: =PMT(J27,G27*12,F27-I27,0)-I27*J27
B28: 5.2.5 | D28: 0 | E28: 0 | F28: =+D28*E28 | G28: 3 | H28: 0 | I28: =+F28*H28 | J28: =+$J$10 | K28: =PMT(J28,G28*12,F28-I28,0)-I28*J28
B29: 5.2.6 | D29: 0 | E29: 0 | F29: =+D29*E29 | G29: 3 | H29: 0 | I29: =+F29*H29 | J29: =+$J$10 | K29: =PMT(J29,G29*12,F29-I29,0)-I29*J29
B30: 5.2.7 | D30: 0 | E30: 0 | F30: =+D30*E30 | G30: 3 | H30: 0 | I30: =+F30*H30 | J30: =+$J$10 | K30: =PMT(J30,G30*12,F30-I30,0)-I30*J30
B31: 5.2.8 | D31: 0 | E31: 0 | F31: =+D31*E31 | G31: 3 | H31: 0 | I31: =+F31*H31 | J31: =+$J$10 | K31: =PMT(J31,G31*12,F31-I31,0)-I31*J31
B32: 5.2.9 | D32: 0 | E32: 0 | F32: =+D32*E32 | G32: 3 | H32: 0 | I32: =+F32*H32 | J32: =+$J$10 | K32: =PMT(J32,G32*12,F32-I32,0)-I32*J32
B33: 5.2.10 | D33: 0 | E33: 0 | F33: =+D33*E33 | G33: 3 | H33: 0 | I33: =+F33*H33 | J33: =+$J$10 | K33: =PMT(J33,G33*12,F33-I33,0)-I33*J33
B34: 5.2.11 | D34: 0 | E34: 0 | F34: =+D34*E34 | G34: 3 | H34: 0 | I34: =+F34*H34 | J34: =+$J$10 | K34: =PMT(J34,G34*12,F34-I34,0)-I34*J34
B35: 5.2.12 | D35: 0 | E35: 0 | F35: =+D35*E35 | G35: 3 | H35: 0 | I35: =+F35*H35 | J35: =+$J$10 | K35: =PMT(J35,G35*12,F35-I35,0)-I35*J35
B36: 5.3 | C36: INSTALACIÓNES Y ADECUACIÓN DE LOCALES | F36: =SUM(F37:F48) | I36: =SUM(I37:I48) | K36: =SUM(K37:K48)*-1
B37: 5.3.1 | D37: 0 | E37: 0 | F37: =+D37*E37 | G37: 8 | H37: 0.5 | I37: =+F37*H37 | J37: =+$J$10 | K37: =PMT(J37,G37*12,F37-I37,0)-I37*J37
B38: 5.3.2 | D38: 0 | E38: 0 | F38: =+D38*E38 | G38: 8 | H38: 0.5 | I38: =+F38*H38 | J38: =+$J$10 | K38: =PMT(J38,G38*12,F38-I38,0)-I38*J38
B39: 5.3.3 | D39: 0 | E39: 0 | F39: =+D39*E39 | G39: 5 | H39: 0 | I39: =+F39*H39 | J39: =+$J$10 | K39: =PMT(J39,G39*12,F39-I39,0)-I39*J39
B40: 5.3.4 | D40: 0 | E40: 0 | F40: =+D40*E40 | G40: 5 | H40: 0 | I40: =+F40*H40 | J40: =+$J$10 | K40: =PMT(J40,G40*12,F40-I40,0)-I40*J40
B41: 5.3.5 | D41: 0 | E41: 0 | F41: =+D41*E41 | G41: 3 | H41: 0 | I41: =+F41*H41 | J41: =+$J$10 | K41: =PMT(J41,G41*12,F41-I41,0)-I41*J41
B42: 5.3.6 | D42: 0 | E42: 0 | F42: =+D42*E42 | G42: 3 | H42: 0 | I42: =+F42*H42 | J42: =+$J$10 | K42: =PMT(J42,G42*12,F42-I42,0)-I42*J42
B43: 5.3.7 | D43: 0 | E43: 0 | F43: =+D43*E43 | G43: 3 | H43: 0 | I43: =+F43*H43 | J43: =+$J$10 | K43: =PMT(J43,G43*12,F43-I43,0)-I43*J43
B44: 5.3.8 | D44: 0 | E44: 0 | F44: =+D44*E44 | G44: 3 | H44: 0 | I44: =+F44*H44 | J44: =+$J$10 | K44: =PMT(J44,G44*12,F44-I44,0)-I44*J44
B45: 5.3.9 | D45: 0 | E45: 0 | F45: =+D45*E45 | G45: 3 | H45: 0 | I45: =+F45*H45 | J45: =+$J$10 | K45: =PMT(J45,G45*12,F45-I45,0)-I45*J45
B46: 5.3.10 | D46: 0 | E46: 0 | F46: =+D46*E46 | G46: 3 | H46: 0 | I46: =+F46*H46 | J46: =+$J$10 | K46: =PMT(J46,G46*12,F46-I46,0)-I46*J46
B47: 5.3.11 | D47: 0 | E47: 0 | F47: =+D47*E47 | G47: 3 | H47: 0 | I47: =+F47*H47 | J47: =+$J$10 | K47: =PMT(J47,G47*12,F47-I47,0)-I47*J47
B48: 5.3.12 | D48: 0 | E48: 0 | F48: =+D48*E48 | G48: 3 | H48: 0 | I48: =+F48*H48 | J48: =+$J$10 | K48: =PMT(J48,G48*12,F48-I48,0)-I48*J48
B49: 5.4 | C49: MEDIOS INFORMÁTICOS Y MEDIOS DE COMUNICACIÓN | F49: =SUM(F50:F61) | I49: =SUM(I50:I61) | K49: =SUM(K50:K61)*-1
B50: 5.4.1 | D50: 0 | E50: 0 | F50: =+D50*E50 | G50: 3 | H50: 0 | I50: =+F50*H50 | J50: =+$J$10 | K50: =PMT(J50,G50*12,F50-I50,0)-I50*J50
B51: 5.4.2 | D51: 0 | E51: 0 | F51: =+D51*E51 | G51: 3 | H51: 0 | I51: =+F51*H51 | J51: =+$J$10 | K51: =PMT(J51,G51*12,F51-I51,0)-I51*J51
B52: 5.4.3 | D52: 0 | E52: 0 | F52: =+D52*E52 | G52: 1 | H52: 0 | I52: =+F52*H52 | J52: =+$J$10 | K52: =PMT(J52,G52*12,F52-I52,0)-I52*J52
B53: 5.4.4 | D53: 0 | E53: 0 | F53: =+D53*E53 | G53: 1 | H53: 0 | I53: =+F53*H53 | J53: =+$J$10 | K53: =PMT(J53,G53*12,F53-I53,0)-I53*J53
B54: 5.4.5 | D54: 0 | E54: 0 | F54: =+D54*E54 | G54: 1 | H54: 0 | I54: =+F54*H54 | J54: =+$J$10 | K54: =PMT(J54,G54*12,F54-I54,0)-I54*J54
B55: 5.4.6 | D55: 0 | E55: 0 | F55: =+D55*E55 | G55: 1 | H55: 0 | I55: =+F55*H55 | J55: =+$J$10 | K55: =PMT(J55,G55*12,F55-I55,0)-I55*J55
B56: 5.4.7 | D56: 0 | E56: 0 | F56: =+D56*E56 | G56: 1 | H56: 0 | I56: =+F56*H56 | J56: =+$J$10 | K56: =PMT(J56,G56*12,F56-I56,0)-I56*J56
B57: 5.4.8 | D57: 0 | E57: 0 | F57: =+D57*E57 | G57: 1 | H57: 0 | I57: =+F57*H57 | J57: =+$J$10 | K57: =PMT(J57,G57*12,F57-I57,0)-I57*J57
B58: 5.4.9 | D58: 0 | E58: 0 | F58: =+D58*E58 | G58: 1 | H58: 0 | I58: =+F58*H58 | J58: =+$J$10 | K58: =PMT(J58,G58*12,F58-I58,0)-I58*J58
B59: 5.4.10 | D59: 0 | E59: 0 | F59: =+D59*E59 | G59: 1 | H59: 0 | I59: =+F59*H59 | J59: =+$J$10 | K59: =PMT(J59,G59*12,F59-I59,0)-I59*J59
B60: 5.4.11 | D60: 0 | E60: 0 | F60: =+D60*E60 | G60: 1 | H60: 0 | I60: =+F60*H60 | J60: =+$J$10 | K60: =PMT(J60,G60*12,F60-I60,0)-I60*J60
B61: 5.4.12 | D61: 0 | E61: 0 | F61: =+D61*E61 | G61: 1 | H61: 0 | I61: =+F61*H61 | J61: =+$J$10 | K61: =PMT(J61,G61*12,F61-I61,0)-I61*J61
B62: 5.5 | C62: MÁQUINAS Y HERRAMIENTAS | F62: =SUM(F63:F74) | I62: =SUM(I63:I74) | K62: =SUM(K63:K74)*-1
B63: 5.5.1 | D63: 0 | E63: 0 | F63: =+D63*E63 | G63: 2 | H63: 0 | I63: =+F63*H63 | J63: =+$J$10 | K63: =PMT(J63,G63*12,F63-I63,0)-I63*J63
B64: 5.5.2 | D64: 0 | E64: 0 | F64: =+D64*E64 | G64: 3 | H64: 0.5 | I64: =+F64*H64 | J64: =+$J$10 | K64: =PMT(J64,G64*12,F64-I64,0)-I64*J64
B65: 5.5.3 | D65: 0 | E65: 0 | F65: =+D65*E65 | G65: 5 | H65: 0.4 | I65: =+F65*H65 | J65: =+$J$10 | K65: =PMT(J65,G65*12,F65-I65,0)-I65*J65
B66: 5.5.4 | D66: 0 | E66: 0 | F66: =+D66*E66 | G66: 3 | H66: 0 | I66: =+F66*H66 | J66: =+$J$10 | K66: =PMT(J66,G66*12,F66-I66,0)-I66*J66
B67: 5.5.5 | D67: 0 | E67: 0 | F67: =+D67*E67 | G67: 1 | H67: 0 | I67: =+F67*H67 | J67: =+$J$10 | K67: =PMT(J67,G67*12,F67-I67,0)-I67*J67
B68: 5.5.6 | D68: 0 | E68: 0 | F68: =+D68*E68 | G68: 1 | H68: 0 | I68: =+F68*H68 | J68: =+$J$10 | K68: =PMT(J68,G68*12,F68-I68,0)-I68*J68
B69: 5.5.7 | D69: 0 | E69: 0 | F69: =+D69*E69 | G69: 1 | H69: 0 | I69: =+F69*H69 | J69: =+$J$10 | K69: =PMT(J69,G69*12,F69-I69,0)-I69*J69
B70: 5.5.8 | D70: 0 | E70: 0 | F70: =+D70*E70 | G70: 1 | H70: 0 | I70: =+F70*H70 | J70: =+$J$10 | K70: =PMT(J70,G70*12,F70-I70,0)-I70*J70
B71: 5.5.9 | D71: 0 | E71: 0 | F71: =+D71*E71 | G71: 1 | H71: 0 | I71: =+F71*H71 | J71: =+$J$10 | K71: =PMT(J71,G71*12,F71-I71,0)-I71*J71
B72: 5.5.10 | D72: 0 | E72: 0 | F72: =+D72*E72 | G72: 1 | H72: 0 | I72: =+F72*H72 | J72: =+$J$10 | K72: =PMT(J72,G72*12,F72-I72,0)-I72*J72
B73: 5.5.11 | D73: 0 | E73: 0 | F73: =+D73*E73 | G73: 1 | H73: 0 | I73: =+F73*H73 | J73: =+$J$10 | K73: =PMT(J73,G73*12,F73-I73,0)-I73*J73
B74: 5.5.12 | D74: 0 | E74: 0 | F74: =+D74*E74 | G74: 1 | H74: 0 | I74: =+F74*H74 | J74: =+$J$10 | K74: =PMT(J74,G74*12,F74-I74,0)-I74*J74
B75: 5.6 | C75: GASTOS DE ORGANIZACIÓN E IMPLEMENTACIÓN | F75: =SUM(F76:F87) | I75: =SUM(I76:I87) | K75: =SUM(K76:K87)*-1
B76: 5.6.1 | F76: =D76*E76 | G76: 3 | H76: 0 | I76: =+F76*H76 | J76: =+$J$10 | K76: =PMT(J76,G76*12,F76-I76,0)-I76*J76
B77: 5.6.2
B78: 5.6.3 | F78: =+D78*E78 | G78: 3 | H78: 0 | I78: =+F78*H78 | J78: =+$J$10 | K78: =PMT(J78,G78*12,F78-I78,0)-I78*J78
B79: 5.6.4 | F79: =+D79*E79 | G79: 3 | H79: 0 | I79: =+F79*H79 | J79: =+$J$10 | K79: =PMT(J79,G79*12,F79-I79,0)-I79*J79
B80: 5.6.5 | F80: =+D80*E80 | G80: 3 | H80: 0 | I80: =+F80*H80 | J80: =+$J$10 | K80: =PMT(J80,G80*12,F80-I80,0)-I80*J80
B81: 5.6.6 | F81: =+D81*E81 | G81: 3 | H81: 0 | I81: =+F81*H81 | J81: =+$J$10 | K81: =PMT(J81,G81*12,F81-I81,0)-I81*J81
B82: 5.6.7 | F82: =+D82*E82 | G82: 3 | H82: 0 | I82: =+F82*H82 | J82: =+$J$10 | K82: =PMT(J82,G82*12,F82-I82,0)-I82*J82
B83: 5.6.8 | F83: =+D83*E83 | G83: 3 | H83: 0 | I83: =+F83*H83 | J83: =+$J$10 | K83: =PMT(J83,G83*12,F83-I83,0)-I83*J83
B84: 5.6.9 | F84: =+D84*E84 | G84: 3 | H84: 0 | I84: =+F84*H84 | J84: =+$J$10 | K84: =PMT(J84,G84*12,F84-I84,0)-I84*J84
B85: 5.6.10 | F85: =+D85*E85 | G85: 3 | H85: 0 | I85: =+F85*H85 | J85: =+$J$10 | K85: =PMT(J85,G85*12,F85-I85,0)-I85*J85
B86: 5.6.11 | F86: =+D86*E86 | G86: 3 | H86: 0 | I86: =+F86*H86 | J86: =+$J$10 | K86: =PMT(J86,G86*12,F86-I86,0)-I86*J86
B87: 5.6.12 | F87: =+D87*E87 | G87: 3 | H87: 0 | I87: =+F87*H87 | J87: =+$J$10 | K87: =PMT(J87,G87*12,F87-I87,0)-I87*J87
C89: TOTAL INVERSIÓN | F89: =+F10+F23+F36+F49+F62+F75 | G89: RECUPERACIÓN DE INVERSIÓN POR AMORTIZACIÓN | K89: =+J8*12*'Hoja de CIERRE'!$AD$45
D91: K para inversiones B.Uso | F91: =+F89-F75+M77 | G91: SALDO A RECUPERAR POR VALOR RESIDUAL | K91: =+K89-F89

Sheet Equipos
A3: ITEM | B3: DESCRIPCION | C3: CANTIDA | D3: PU | E3: $
C4: 0 | D4: 0
C5: 0 | D5: 0
A6: 3 | C6: 0 | D6: 0 | E6: =C6*D6
A7: 4 | C7: 0 | D7: 0
A8: 5 | C8: 0 | D8: 0
A9: 6 | C9: 0 | D9: 0
A10: 7 | C10: 0 | D10: 0 | E10: =C10*D10
A11: 8 | C11: 0 | D11: 0
A12: 9 | C12: 0 | D12: 0 | E12: =C12*D12
A13: 10 | C13: 0 | D13: 0 | E13: =C13*D13
A14: 11 | C14: 0 | D14: 0
A15: 12 | C15: 0 | D15: 0
A16: 13 | C16: 0 | D16: 0
A17: 14 | C17: 0 | D17: 0
A18: 15 | C18: 0 | D18: 0
A19: 16 | C19: 0 | D19: 0
A20: 17 | C20: 0 | D20: 0
A21: 18 | C21: 0 | D21: 0
A22: 19 | C22: 0 | D22: 0
A23: 20 | C23: 0 | D23: 0
A24: 21 | C24: 0 | D24: 0
A25: 22 | C25: 0 | D25: 0
... A28: 25 | C28: 0 | D28: 0
A29: 26 | C29: 0 | D29: 0 | E29: =C29*D29
A30: 27 | C30: 0 | D30: 0
A31: 28 | C31: 0 | D31: 0 | E31: =C31*D31
A32: 29 | C32: 0 | D32: 0 | E32: =C32*D32
A33: 30 | C33: 0 | D33: 0
A34: 31 | C34: 0 | D34: 0
A35: 32 | C35: 0 | D35: 0
A36: 33 | C36: 0 | D36: 0
A37: 34 | C37: 0 | D37: 0
A38: 35 | C38: 0 | D38: 0
A39: 36 | C39: 0 | D39: 0 | E39: =C39*D39
A40: 37 | C40: 0 | D40: 0 | E40: =C40*D40
A41: 38 | C41: 0 | D41: 0 | E41: =C41*D41
A42: 39 | C42: 0 | D42: 0 | E42: =C42*D42
A43: 40 | C43: 0 | D43: 0 | E43: =C43*D43
A44: 41 | C44: 0 | D44: 0 | E44: =C44*D44
A45: 42 | C45: 0 | D45: 0 | E45: =C45*D45
A46: 43 | C46: 0 | D46: 0 | E46: =C46*D46
A47: 44 | C47: 0 | D47: 0 | E47: =C47*D47
A48: 45 | C48: 0 | D48: 0 | E48: =C48*D48
A49: 46 | C49: 0 | D49: 0 | E49: =C49*D49
A50: 47 | C50: 0 | D50: 0 | E50: =C50*D50
A51: 48 | C51: 0 | D51: 0
A52: 49 | C52: 0 | D52: 0
A53: 50 | C53: 0 | D53: 0
A54: 51 | C54: 0 | D54: 0
A55: 52 | C55: 0 | D55: 0
A56: 53 | C56: 0 | D56: 0
A57: 54 | C57: 0 | D57: 0
A58: 55 | C58: 0 | D58: 0
A59: 56 | C59: 0 | D59: 0
A60: 57 | C60: 0 | D60: 0 | E60: =C60*D60
A61: 58 | C61: 0 | D61: 0
A62: 59 | C62: 0 | D62: 0
A63: 60 | C63: 0 | D63: 0
A64: 61 | C64: 0 | D64: 0
A65: 62 | C65: 0 | D65: 0
A66: 63 | C66: 0 | D66: 0
A67: 64 | C67: 0 | D67: 0 | E67: =C67*D67
A68: 65 | C68: 0 | D68: 0
A69: 66 | C69: 0 | D69: 0
A70: 67 | C70: 0 | D70: 0
A71: 68 | C71: 0 | D71: 0
A72: 72 | C72: 0 | D72: 0
A73: 76 | C73: 0 | D73: 0 | E73: =C73*D73
A74: 77 | C74: 0 | D74: 0 | E74: =C74*D74
A75: 80 | C75: 0 | D75: 0 | E75: =C75*D75
A76: 81 | C76: 0 | D76: 0 | E76: =C76*D76
A77: 82 | C77: 0 | D77: 0 | E77: =C77*D77
A78: 83 | C78: 0 | D78: 0 | E78: =C78*D78
A79: 84 | C79: 0 | D79: 0 | E79: =C79*D79
C80: 0 | D80: 0 | E80: =C80*D80
C81: 0 | D81: 0 | E81: =C81*D81
C82: 0 | D82: 0
C83: 0 | D83: 0
C84: 0 | D84: 0 | E84: =C84*D84
C85: 0 | D85: 0
C86: 0 | D86: 0
C87: 0 | D87: 0
C88: 0 | D88: 0 | E88: =C88*D88
C89: 0 | D89: 0 | E89: =C89*D89
C90: 0 | D90: 0 | E90: =C90*D90
C91: 0 | D91: 0 | E91: =C91*D91
C92: 0 | D92: 0 | E92: =C92*D92
C93: 0 | D93: 0 | E93: =C93*D93
C94: 0 | D94: 0
C95: 0 | D95: 0
C96: 0 | D96: 0
C97: 0 | D97: 0
C98: 0 | D98: 0
C99: 0 | D99: 0
C100: 0 | D100: 0
C101: 0 | D101: 0
C102: 0 | D102: 0
C103: 0 | D103: 0
C104: 0 | D104: 0
...
